{
  "start": "2025-09-01",
  "end": "2026-03-14",
  "groups": [
    {
      "market": "ASSISTS",
      "line": 0.5,
      "window": 5,
      "count": 41882,
      "accuracy": 0.7368559285611957,
      "brier": 0.19763577922639544,
      "calibration_params": {
        "t": 1.1500000000000004,
        "b": -0.15,
        "brier_post": 0.1946776027001369
      },
      "calibration": [
        {
          "bin": 2,
          "expected": 0.1812692469220181,
          "observed": 0.21758261494252873,
          "count": 11136
        },
        {
          "bin": 3,
          "expected": 0.25357934262735526,
          "observed": 0.20592592592592593,
          "count": 675
        },
        {
          "bin": 4,
          "expected": 0.33393090281632737,
          "observed": 0.26235541535226076,
          "count": 7608
        },
        {
          "bin": 5,
          "expected": 0.4525368082589568,
          "observed": 0.3188546469303567,
          "count": 4121
        },
        {
          "bin": 6,
          "expected": 0.5498866821844973,
          "observed": 0.36089494163424124,
          "count": 2056
        },
        {
          "bin": 7,
          "expected": 0.6470586630279278,
          "observed": 0.3836875358989087,
          "count": 1741
        },
        {
          "bin": 8,
          "expected": 0.7632145549875322,
          "observed": 0.4828767123287671,
          "count": 292
        },
        {
          "bin": 9,
          "expected": 0.8530293935011511,
          "observed": 0.40186915887850466,
          "count": 107
        },
        {
          "bin": 10,
          "expected": 0.9311863149489475,
          "observed": 0.3333333333333333,
          "count": 6
        }
      ]
    },
    {
      "market": "ASSISTS",
      "line": 0.5,
      "window": 10,
      "count": 41882,
      "accuracy": 0.7454992598252232,
      "brier": 0.18723007439708653,
      "calibration_params": {
        "t": 1.2000000000000004,
        "b": -0.15,
        "brier_post": 0.18500865943764452
      },
      "calibration": [
        {
          "bin": 1,
          "expected": 0.09516258196404045,
          "observed": 0.1714503816793893,
          "count": 6550
        },
        {
          "bin": 2,
          "expected": 0.17580925954284712,
          "observed": 0.20319786808794138,
          "count": 7505
        },
        {
          "bin": 3,
          "expected": 0.2584008077748696,
          "observed": 0.23960695389266817,
          "count": 6615
        },
        {
          "bin": 4,
          "expected": 0.3571363925452147,
          "observed": 0.2838270616493195,
          "count": 7494
        },
        {
          "bin": 5,
          "expected": 0.4541210924212565,
          "observed": 0.34265423879272083,
          "count": 2253
        },
        {
          "bin": 6,
          "expected": 0.5364881407839518,
          "observed": 0.406807131280389,
          "count": 2468
        },
        {
          "bin": 7,
          "expected": 0.645244858382663,
          "observed": 0.4180633147113594,
          "count": 1074
        },
        {
          "bin": 8,
          "expected": 0.7475370485337781,
          "observed": 0.538860103626943,
          "count": 193
        },
        {
          "bin": 9,
          "expected": 0.8512591202724779,
          "observed": 0.31343283582089554,
          "count": 67
        },
        {
          "bin": 10,
          "expected": 0.9421384490681273,
          "observed": 0.25,
          "count": 4
        }
      ]
    },
    {
      "market": "ASSISTS",
      "line": 0.5,
      "window": 20,
      "count": 41882,
      "accuracy": 0.7510625089537272,
      "brier": 0.18232243202996418,
      "calibration_params": {
        "t": 1.1500000000000004,
        "b": -0.15,
        "brier_post": 0.18068004937381613
      },
      "calibration": [
        {
          "bin": 1,
          "expected": 0.07641523470048175,
          "observed": 0.15178571428571427,
          "count": 5488
        },
        {
          "bin": 2,
          "expected": 0.15779040715506262,
          "observed": 0.18277814064881343,
          "count": 9186
        },
        {
          "bin": 3,
          "expected": 0.2540409758024252,
          "observed": 0.23527638190954775,
          "count": 9950
        },
        {
          "bin": 4,
          "expected": 0.3567640412870255,
          "observed": 0.29686776731985803,
          "count": 6481
        },
        {
          "bin": 5,
          "expected": 0.45018346852986363,
          "observed": 0.3818747838118298,
          "count": 2891
        },
        {
          "bin": 6,
          "expected": 0.5400828954549034,
          "observed": 0.4391927774827403,
          "count": 1883
        },
        {
          "bin": 7,
          "expected": 0.6395423067741415,
          "observed": 0.4183350895679663,
          "count": 949
        },
        {
          "bin": 8,
          "expected": 0.7401520138146558,
          "observed": 0.49640287769784175,
          "count": 139
        },
        {
          "bin": 9,
          "expected": 0.8595492318753708,
          "observed": 0.22,
          "count": 50
        },
        {
          "bin": 10,
          "expected": 0.9421384490681273,
          "observed": 0.25,
          "count": 4
        }
      ]
    },
    {
      "market": "GOALS",
      "line": 0.5,
      "window": 5,
      "count": 41882,
      "accuracy": 0.8340814669786543,
      "brier": 0.13996103947551702,
      "calibration_params": {
        "t": 0.8500000000000001,
        "b": -0.15,
        "brier_post": 0.13708754946904445
      },
      "calibration": [
        {
          "bin": 2,
          "expected": 0.1812692469220181,
          "observed": 0.15362106803218728,
          "count": 10936
        },
        {
          "bin": 3,
          "expected": 0.25126403096954014,
          "observed": 0.12199312714776632,
          "count": 582
        },
        {
          "bin": 4,
          "expected": 0.33411555862224146,
          "observed": 0.22454859777180178,
          "count": 5206
        },
        {
          "bin": 5,
          "expected": 0.45242627614558184,
          "observed": 0.2369995398067188,
          "count": 2173
        },
        {
          "bin": 6,
          "expected": 0.549866108087489,
          "observed": 0.30120481927710846,
          "count": 830
        },
        {
          "bin": 7,
          "expected": 0.640089234023058,
          "observed": 0.26572327044025157,
          "count": 636
        },
        {
          "bin": 8,
          "expected": 0.7642817308158909,
          "observed": 0.2571428571428571,
          "count": 35
        },
        {
          "bin": 9,
          "expected": 0.8618110400981516,
          "observed": 0.47619047619047616,
          "count": 21
        }
      ]
    },
    {
      "market": "GOALS",
      "line": 0.5,
      "window": 10,
      "count": 41882,
      "accuracy": 0.8397640991356669,
      "brier": 0.13195117808708773,
      "calibration_params": {
        "t": 1.0000000000000002,
        "b": -0.15,
        "brier_post": 0.13041771634270116
      },
      "calibration": [
        {
          "bin": 1,
          "expected": 0.09516258196404047,
          "observed": 0.12436633997972288,
          "count": 8877
        },
        {
          "bin": 2,
          "expected": 0.1740067442291697,
          "observed": 0.16271093428453834,
          "count": 7289
        },
        {
          "bin": 3,
          "expected": 0.25774738072595166,
          "observed": 0.1921487603305785,
          "count": 4840
        },
        {
          "bin": 4,
          "expected": 0.3565598187561244,
          "observed": 0.2452193475815523,
          "count": 4445
        },
        {
          "bin": 5,
          "expected": 0.4542815141987501,
          "observed": 0.28961175236096537,
          "count": 953
        },
        {
          "bin": 6,
          "expected": 0.5311494631798989,
          "observed": 0.35013262599469497,
          "count": 754
        },
        {
          "bin": 7,
          "expected": 0.6346582903442576,
          "observed": 0.2469879518072289,
          "count": 332
        },
        {
          "bin": 8,
          "expected": 0.75965623880531,
          "observed": 0.23809523809523808,
          "count": 21
        },
        {
          "bin": 9,
          "expected": 0.8646647167633873,
          "observed": 0.42105263157894735,
          "count": 19
        }
      ]
    },
    {
      "market": "GOALS",
      "line": 0.5,
      "window": 20,
      "count": 41882,
      "accuracy": 0.8424144023685592,
      "brier": 0.12876986027486767,
      "calibration_params": {
        "t": 1.0500000000000003,
        "b": -0.15,
        "brier_post": 0.12766346203618345
      },
      "calibration": [
        {
          "bin": 1,
          "expected": 0.07097517356521482,
          "observed": 0.10029268292682927,
          "count": 10250
        },
        {
          "bin": 2,
          "expected": 0.1550081991600449,
          "observed": 0.15067035539476484,
          "count": 9398
        },
        {
          "bin": 3,
          "expected": 0.25118762139905465,
          "observed": 0.20621391256530108,
          "count": 7274
        },
        {
          "bin": 4,
          "expected": 0.3563662975277159,
          "observed": 0.2651900628554325,
          "count": 3341
        },
        {
          "bin": 5,
          "expected": 0.44827441370781684,
          "observed": 0.33250414593698174,
          "count": 1206
        },
        {
          "bin": 6,
          "expected": 0.534281139444233,
          "observed": 0.3154929577464789,
          "count": 355
        },
        {
          "bin": 7,
          "expected": 0.6322002900201144,
          "observed": 0.23890784982935154,
          "count": 293
        },
        {
          "bin": 8,
          "expected": 0.7612656403972761,
          "observed": 0.25,
          "count": 20
        },
        {
          "bin": 9,
          "expected": 0.8646647167633873,
          "observed": 0.42105263157894735,
          "count": 19
        }
      ]
    },
    {
      "market": "POINTS",
      "line": 0.5,
      "window": 5,
      "count": 42042,
      "accuracy": 0.6546786546786547,
      "brier": 0.2362023803336901,
      "calibration_params": {
        "t": 1.5000000000000007,
        "b": -0.15,
        "brier_post": 0.23084204316727258
      },
      "calibration": [
        {
          "bin": 2,
          "expected": 0.1812692469220181,
          "observed": 0.2700803212851406,
          "count": 8964
        },
        {
          "bin": 3,
          "expected": 0.2550632969394737,
          "observed": 0.2792207792207792,
          "count": 616
        },
        {
          "bin": 4,
          "expected": 0.3345328808652135,
          "observed": 0.32756223935296347,
          "count": 7913
        },
        {
          "bin": 5,
          "expected": 0.4526400165379134,
          "observed": 0.3855267954794021,
          "count": 5486
        },
        {
          "bin": 6,
          "expected": 0.549880257834013,
          "observed": 0.4497184231697506,
          "count": 3729
        },
        {
          "bin": 7,
          "expected": 0.6528180863672383,
          "observed": 0.5020661157024794,
          "count": 4356
        },
        {
          "bin": 8,
          "expected": 0.768026290984027,
          "observed": 0.5793000744601638,
          "count": 1343
        },
        {
          "bin": 9,
          "expected": 0.8518602084350686,
          "observed": 0.6107011070110702,
          "count": 542
        },
        {
          "bin": 10,
          "expected": 0.9285245563546004,
          "observed": 0.5606060606060606,
          "count": 66
        }
      ]
    },
    {
      "market": "POINTS",
      "line": 0.5,
      "window": 10,
      "count": 42042,
      "accuracy": 0.6638837353123067,
      "brier": 0.22400598432586938,
      "calibration_params": {
        "t": 1.5000000000000007,
        "b": -0.15,
        "brier_post": 0.2202603107674712
      },
      "calibration": [
        {
          "bin": 1,
          "expected": 0.09516258196404048,
          "observed": 0.21729957805907174,
          "count": 3792
        },
        {
          "bin": 2,
          "expected": 0.1765493449473224,
          "observed": 0.2433522831468916,
          "count": 5453
        },
        {
          "bin": 3,
          "expected": 0.25878721076322275,
          "observed": 0.27593507410021173,
          "count": 5668
        },
        {
          "bin": 4,
          "expected": 0.36027705942193156,
          "observed": 0.3403504779244424,
          "count": 8788
        },
        {
          "bin": 5,
          "expected": 0.4541585424339406,
          "observed": 0.39056434756643776,
          "count": 3349
        },
        {
          "bin": 6,
          "expected": 0.542246130383688,
          "observed": 0.47789511365670306,
          "count": 5587
        },
        {
          "bin": 7,
          "expected": 0.6525002407104052,
          "observed": 0.5353846153846153,
          "count": 3250
        },
        {
          "bin": 8,
          "expected": 0.7515649025333037,
          "observed": 0.6161943319838057,
          "count": 1235
        },
        {
          "bin": 9,
          "expected": 0.8477713028111696,
          "observed": 0.6301369863013698,
          "count": 365
        },
        {
          "bin": 10,
          "expected": 0.9315876791275376,
          "observed": 0.5882352941176471,
          "count": 34
        }
      ]
    },
    {
      "market": "POINTS",
      "line": 0.5,
      "window": 20,
      "count": 42042,
      "accuracy": 0.6726131011845298,
      "brier": 0.21856125060050496,
      "calibration_params": {
        "t": 1.3500000000000005,
        "b": -0.15,
        "brier_post": 0.21634862215210102
      },
      "calibration": [
        {
          "bin": 1,
          "expected": 0.07926747982358157,
          "observed": 0.1865766146053187,
          "count": 2369
        },
        {
          "bin": 2,
          "expected": 0.15903343230484604,
          "observed": 0.21170852493809691,
          "count": 5654
        },
        {
          "bin": 3,
          "expected": 0.2563327722707179,
          "observed": 0.27410931878844147,
          "count": 8617
        },
        {
          "bin": 4,
          "expected": 0.35915892107635056,
          "observed": 0.3277278060226828,
          "count": 7671
        },
        {
          "bin": 5,
          "expected": 0.45044038109959483,
          "observed": 0.40715402658326816,
          "count": 5116
        },
        {
          "bin": 6,
          "expected": 0.5436591552977383,
          "observed": 0.49946501176974106,
          "count": 4673
        },
        {
          "bin": 7,
          "expected": 0.645169425618091,
          "observed": 0.5554903112155021,
          "count": 3406
        },
        {
          "bin": 8,
          "expected": 0.7443150904676389,
          "observed": 0.6328767123287671,
          "count": 1095
        },
        {
          "bin": 9,
          "expected": 0.8463267584608934,
          "observed": 0.629757785467128,
          "count": 289
        },
        {
          "bin": 10,
          "expected": 0.9361573610947661,
          "observed": 0.48,
          "count": 25
        }
      ]
    },
    {
      "market": "POINTS",
      "line": 1.5,
      "window": 5,
      "count": 42042,
      "accuracy": 0.9057846914989772,
      "brier": 0.08281975483095168,
      "calibration_params": {
        "t": 0.8500000000000001,
        "b": -0.15,
        "brier_post": 0.08097350966363889
      },
      "calibration": [
        {
          "bin": 1,
          "expected": 0.03908887116371983,
          "observed": 0.06105299262562168,
          "count": 17493
        },
        {
          "bin": 2,
          "expected": 0.15024646391195945,
          "observed": 0.1144872490504612,
          "count": 9215
        },
        {
          "bin": 3,
          "expected": 0.26424111765711533,
          "observed": 0.15612516644474034,
          "count": 3004
        },
        {
          "bin": 4,
          "expected": 0.3391606997170162,
          "observed": 0.18181818181818182,
          "count": 1430
        },
        {
          "bin": 5,
          "expected": 0.43492912586683424,
          "observed": 0.23501945525291829,
          "count": 1285
        },
        {
          "bin": 6,
          "expected": 0.5641845530723381,
          "observed": 0.2607758620689655,
          "count": 464
        },
        {
          "bin": 7,
          "expected": 0.6594987102464939,
          "observed": 0.34523809523809523,
          "count": 84
        },
        {
          "bin": 8,
          "expected": 0.7431552531442989,
          "observed": 0.4,
          "count": 20
        },
        {
          "bin": 9,
          "expected": 0.8052644133857522,
          "observed": 0.21052631578947367,
          "count": 19
        },
        {
          "bin": 10,
          "expected": 0.9084218055563291,
          "observed": 1.0,
          "count": 1
        }
      ]
    },
    {
      "market": "POINTS",
      "line": 1.5,
      "window": 10,
      "count": 42042,
      "accuracy": 0.908662765805623,
      "brier": 0.079136926735554,
      "calibration_params": {
        "t": 0.9500000000000002,
        "b": -0.15,
        "brier_post": 0.07811540508334362
      },
      "calibration": [
        {
          "bin": 1,
          "expected": 0.04135504853023758,
          "observed": 0.05539850639213535,
          "count": 23701
        },
        {
          "bin": 2,
          "expected": 0.15030103959743257,
          "observed": 0.11945895272532477,
          "count": 7467
        },
        {
          "bin": 3,
          "expected": 0.2472615299405179,
          "observed": 0.1627491817911336,
          "count": 3361
        },
        {
          "bin": 4,
          "expected": 0.3326658692680185,
          "observed": 0.23594324750394113,
          "count": 1903
        },
        {
          "bin": 5,
          "expected": 0.4363459867718937,
          "observed": 0.2759103641456583,
          "count": 714
        },
        {
          "bin": 6,
          "expected": 0.5578920508380739,
          "observed": 0.2842809364548495,
          "count": 299
        },
        {
          "bin": 7,
          "expected": 0.6475083089657108,
          "observed": 0.52,
          "count": 50
        },
        {
          "bin": 8,
          "expected": 0.7198354434773232,
          "observed": 0.18181818181818182,
          "count": 11
        },
        {
          "bin": 9,
          "expected": 0.800851726528544,
          "observed": 0.21428571428571427,
          "count": 14
        },
        {
          "bin": 10,
          "expected": 0.9084218055563291,
          "observed": 1.0,
          "count": 1
        }
      ]
    },
    {
      "market": "POINTS",
      "line": 1.5,
      "window": 20,
      "count": 42042,
      "accuracy": 0.9093763379477665,
      "brier": 0.07778481181025959,
      "calibration_params": {
        "t": 1.0000000000000002,
        "b": -0.15,
        "brier_post": 0.07709573784074669
      },
      "calibration": [
        {
          "bin": 1,
          "expected": 0.04026093099422868,
          "observed": 0.0492515890916547,
          "count": 24385
        },
        {
          "bin": 2,
          "expected": 0.14178802103472934,
          "observed": 0.12056392805055907,
          "count": 8228
        },
        {
          "bin": 3,
          "expected": 0.24577495222128262,
          "observed": 0.18195679796696315,
          "count": 3935
        },
        {
          "bin": 4,
          "expected": 0.3375697362988774,
          "observed": 0.2605945604048071,
          "count": 1581
        },
        {
          "bin": 5,
          "expected": 0.4397428632309411,
          "observed": 0.29672447013487474,
          "count": 519
        },
        {
          "bin": 6,
          "expected": 0.5670213473887054,
          "observed": 0.2818181818181818,
          "count": 220
        },
        {
          "bin": 7,
          "expected": 0.6466868420110821,
          "observed": 0.4074074074074074,
          "count": 27
        },
        {
          "bin": 8,
          "expected": 0.7106194291685177,
          "observed": 0.2,
          "count": 5
        },
        {
          "bin": 9,
          "expected": 0.800851726528544,
          "observed": 0.21428571428571427,
          "count": 14
        },
        {
          "bin": 10,
          "expected": 0.9084218055563291,
          "observed": 1.0,
          "count": 1
        }
      ]
    },
    {
      "market": "SAVES",
      "line": 24.5,
      "window": 5,
      "count": 4500,
      "accuracy": 0.7533333333333333,
      "brier": 0.22314524449426562,
      "calibration_params": {
        "t": 1.5000000000000007,
        "b": 0.15,
        "brier_post": 0.21455849847155428
      },
      "calibration": [
        {
          "bin": 1,
          "expected": 0.01093487763947932,
          "observed": 0.22427077600440287,
          "count": 3634
        },
        {
          "bin": 2,
          "expected": 0.14546884198773768,
          "observed": 0.2717391304347826,
          "count": 276
        },
        {
          "bin": 3,
          "expected": 0.24207251822748804,
          "observed": 0.32298136645962733,
          "count": 161
        },
        {
          "bin": 4,
          "expected": 0.34414269666357944,
          "observed": 0.2706766917293233,
          "count": 133
        },
        {
          "bin": 5,
          "expected": 0.4437684213819497,
          "observed": 0.27419354838709675,
          "count": 62
        },
        {
          "bin": 6,
          "expected": 0.550594792139615,
          "observed": 0.2777777777777778,
          "count": 36
        },
        {
          "bin": 7,
          "expected": 0.6420683454396872,
          "observed": 0.3333333333333333,
          "count": 39
        },
        {
          "bin": 8,
          "expected": 0.7417738050385209,
          "observed": 0.3235294117647059,
          "count": 34
        },
        {
          "bin": 9,
          "expected": 0.8586247034005564,
          "observed": 0.25,
          "count": 12
        },
        {
          "bin": 10,
          "expected": 0.9458661082862202,
          "observed": 0.1111111111111111,
          "count": 9
        }
      ]
    },
    {
      "market": "SAVES",
      "line": 24.5,
      "window": 10,
      "count": 4500,
      "accuracy": 0.7593333333333333,
      "brier": 0.2206025598772483,
      "calibration_params": {
        "t": 1.5000000000000007,
        "b": 0.15,
        "brier_post": 0.21041680322065465
      },
      "calibration": [
        {
          "bin": 1,
          "expected": 0.011087183720814435,
          "observed": 0.21976016684045882,
          "count": 3836
        },
        {
          "bin": 2,
          "expected": 0.14516039701602398,
          "observed": 0.33865814696485624,
          "count": 313
        },
        {
          "bin": 3,
          "expected": 0.24678664054154398,
          "observed": 0.3560606060606061,
          "count": 132
        },
        {
          "bin": 4,
          "expected": 0.3448254920964046,
          "observed": 0.3333333333333333,
          "count": 66
        },
        {
          "bin": 5,
          "expected": 0.4459691008569379,
          "observed": 0.25,
          "count": 48
        },
        {
          "bin": 6,
          "expected": 0.5395685003239638,
          "observed": 0.3076923076923077,
          "count": 26
        },
        {
          "bin": 7,
          "expected": 0.633263649294357,
          "observed": 0.3333333333333333,
          "count": 15
        },
        {
          "bin": 8,
          "expected": 0.7453846375739414,
          "observed": 0.375,
          "count": 16
        },
        {
          "bin": 9,
          "expected": 0.8715932324312583,
          "observed": 0.0,
          "count": 4
        },
        {
          "bin": 10,
          "expected": 0.966651618749847,
          "observed": 0.16666666666666666,
          "count": 6
        }
      ]
    },
    {
      "market": "SAVES",
      "line": 24.5,
      "window": 20,
      "count": 4500,
      "accuracy": 0.762,
      "brier": 0.2213063738915308,
      "calibration_params": {
        "t": 1.5000000000000007,
        "b": 0.15,
        "brier_post": 0.2101843844516269
      },
      "calibration": [
        {
          "bin": 1,
          "expected": 0.011514626507948936,
          "observed": 0.22259136212624583,
          "count": 3913
        },
        {
          "bin": 2,
          "expected": 0.14041647455092965,
          "observed": 0.3367003367003367,
          "count": 297
        },
        {
          "bin": 3,
          "expected": 0.24142030700408174,
          "observed": 0.3684210526315789,
          "count": 114
        },
        {
          "bin": 4,
          "expected": 0.34224431611924033,
          "observed": 0.21666666666666667,
          "count": 60
        },
        {
          "bin": 5,
          "expected": 0.4407779134279846,
          "observed": 0.25806451612903225,
          "count": 31
        },
        {
          "bin": 6,
          "expected": 0.5555622075768291,
          "observed": 0.4444444444444444,
          "count": 9
        },
        {
          "bin": 7,
          "expected": 0.6327251400031916,
          "observed": 0.35714285714285715,
          "count": 14
        },
        {
          "bin": 8,
          "expected": 0.7492327580389798,
          "observed": 0.42857142857142855,
          "count": 14
        },
        {
          "bin": 9,
          "expected": 0.8715932324312583,
          "observed": 0.0,
          "count": 4
        },
        {
          "bin": 10,
          "expected": 0.966651618749847,
          "observed": 0.16666666666666666,
          "count": 6
        }
      ]
    },
    {
      "market": "SAVES",
      "line": 26.5,
      "window": 5,
      "count": 4500,
      "accuracy": 0.808,
      "brier": 0.1801306583640592,
      "calibration_params": {
        "t": 1.5000000000000007,
        "b": -0.05,
        "brier_post": 0.17515395448249313
      },
      "calibration": [
        {
          "bin": 1,
          "expected": 0.008522967914141956,
          "observed": 0.17955304392499358,
          "count": 3893
        },
        {
          "bin": 2,
          "expected": 0.14217999779464965,
          "observed": 0.2242152466367713,
          "count": 223
        },
        {
          "bin": 3,
          "expected": 0.24059470585817055,
          "observed": 0.2265625,
          "count": 128
        },
        {
          "bin": 4,
          "expected": 0.34640034776247747,
          "observed": 0.2,
          "count": 40
        },
        {
          "bin": 5,
          "expected": 0.443915655855618,
          "observed": 0.24390243902439024,
          "count": 41
        },
        {
          "bin": 6,
          "expected": 0.5448963900167121,
          "observed": 0.42857142857142855,
          "count": 28
        },
        {
          "bin": 7,
          "expected": 0.6255419222000153,
          "observed": 0.25,
          "count": 24
        },
        {
          "bin": 8,
          "expected": 0.7702973380931706,
          "observed": 0.2,
          "count": 10
        },
        {
          "bin": 9,
          "expected": 0.838413502496819,
          "observed": 0.0,
          "count": 5
        },
        {
          "bin": 10,
          "expected": 0.9683526378528078,
          "observed": 0.25,
          "count": 4
        }
      ]
    },
    {
      "market": "SAVES",
      "line": 26.5,
      "window": 10,
      "count": 4500,
      "accuracy": 0.8113333333333334,
      "brier": 0.17974193795849971,
      "calibration_params": {
        "t": 1.5000000000000007,
        "b": 0.15,
        "brier_post": 0.1737441611698342
      },
      "calibration": [
        {
          "bin": 1,
          "expected": 0.00865162672711808,
          "observed": 0.18098010674429887,
          "count": 4122
        },
        {
          "bin": 2,
          "expected": 0.13959033572101162,
          "observed": 0.25405405405405407,
          "count": 185
        },
        {
          "bin": 3,
          "expected": 0.2454935071180636,
          "observed": 0.23076923076923078,
          "count": 65
        },
        {
          "bin": 4,
          "expected": 0.34032077177761116,
          "observed": 0.21951219512195122,
          "count": 41
        },
        {
          "bin": 5,
          "expected": 0.44620868152170184,
          "observed": 0.2631578947368421,
          "count": 19
        },
        {
          "bin": 6,
          "expected": 0.5488602131349464,
          "observed": 0.25,
          "count": 8
        },
        {
          "bin": 7,
          "expected": 0.6188418197420846,
          "observed": 0.4166666666666667,
          "count": 12
        },
        {
          "bin": 8,
          "expected": 0.7738868201701488,
          "observed": 0.0,
          "count": 4
        },
        {
          "bin": 9,
          "expected": 0.8621322121479809,
          "observed": 0.0,
          "count": 2
        },
        {
          "bin": 10,
          "expected": 0.9683526378528078,
          "observed": 0.25,
          "count": 4
        }
      ]
    },
    {
      "market": "SAVES",
      "line": 26.5,
      "window": 20,
      "count": 4500,
      "accuracy": 0.8117777777777778,
      "brier": 0.18037666124342164,
      "calibration_params": {
        "t": 1.5000000000000007,
        "b": 0.15,
        "brier_post": 0.17385264725140143
      },
      "calibration": [
        {
          "bin": 1,
          "expected": 0.008436538972431113,
          "observed": 0.18214370971592264,
          "count": 4189
        },
        {
          "bin": 2,
          "expected": 0.14001140180368538,
          "observed": 0.2545454545454545,
          "count": 165
        },
        {
          "bin": 3,
          "expected": 0.247323556463483,
          "observed": 0.1836734693877551,
          "count": 49
        },
        {
          "bin": 4,
          "expected": 0.33076053056598037,
          "observed": 0.25,
          "count": 16
        },
        {
          "bin": 5,
          "expected": 0.4493398849214161,
          "observed": 0.26666666666666666,
          "count": 15
        },
        {
          "bin": 6,
          "expected": 0.5402859268379302,
          "observed": 0.3333333333333333,
          "count": 6
        },
        {
          "bin": 7,
          "expected": 0.6188418197420846,
          "observed": 0.4166666666666667,
          "count": 12
        },
        {
          "bin": 8,
          "expected": 0.7738868201701488,
          "observed": 0.0,
          "count": 4
        },
        {
          "bin": 9,
          "expected": 0.8621322121479809,
          "observed": 0.0,
          "count": 2
        },
        {
          "bin": 10,
          "expected": 0.9683526378528078,
          "observed": 0.25,
          "count": 4
        }
      ]
    },
    {
      "market": "SOG",
      "line": 2.5,
      "window": 5,
      "count": 29990,
      "accuracy": 0.6782260753584528,
      "brier": 0.21159293518753214,
      "calibration_params": {
        "t": 1.3500000000000005,
        "b": -0.15,
        "brier_post": 0.20596352819620256
      },
      "calibration": [
        {
          "bin": 1,
          "expected": 0.08030139707139416,
          "observed": 0.16695957820738136,
          "count": 3414
        },
        {
          "bin": 2,
          "expected": 0.16537463168682767,
          "observed": 0.1994280266920877,
          "count": 5245
        },
        {
          "bin": 3,
          "expected": 0.24475399927585922,
          "observed": 0.2566287878787879,
          "count": 4224
        },
        {
          "bin": 4,
          "expected": 0.3417439102814971,
          "observed": 0.28501033222063266,
          "count": 6291
        },
        {
          "bin": 5,
          "expected": 0.45285862482931727,
          "observed": 0.34978486459124275,
          "count": 3951
        },
        {
          "bin": 6,
          "expected": 0.5548963006752797,
          "observed": 0.39299867899603697,
          "count": 3028
        },
        {
          "bin": 7,
          "expected": 0.6540267322836576,
          "observed": 0.47344689378757515,
          "count": 1996
        },
        {
          "bin": 8,
          "expected": 0.7509926360100073,
          "observed": 0.4906427990235964,
          "count": 1229
        },
        {
          "bin": 9,
          "expected": 0.8426752409801844,
          "observed": 0.572289156626506,
          "count": 498
        },
        {
          "bin": 10,
          "expected": 0.9268256626193491,
          "observed": 0.5877192982456141,
          "count": 114
        }
      ]
    },
    {
      "market": "SOG",
      "line": 2.5,
      "window": 10,
      "count": 30098,
      "accuracy": 0.6931025317296831,
      "brier": 0.20364470726626704,
      "calibration_params": {
        "t": 1.1000000000000003,
        "b": -0.15,
        "brier_post": 0.20020760254943756
      },
      "calibration": [
        {
          "bin": 1,
          "expected": 0.08032622942364827,
          "observed": 0.16613007083065034,
          "count": 1553
        },
        {
          "bin": 2,
          "expected": 0.15834168664519804,
          "observed": 0.1690793283149971,
          "count": 5181
        },
        {
          "bin": 3,
          "expected": 0.2510366672270681,
          "observed": 0.23133982382939267,
          "count": 6471
        },
        {
          "bin": 4,
          "expected": 0.34641557255037686,
          "observed": 0.2842752262250299,
          "count": 5857
        },
        {
          "bin": 5,
          "expected": 0.44684942450567405,
          "observed": 0.351555929352397,
          "count": 4756
        },
        {
          "bin": 6,
          "expected": 0.5507820469463844,
          "observed": 0.4197940883427433,
          "count": 3011
        },
        {
          "bin": 7,
          "expected": 0.644926625717972,
          "observed": 0.5158163265306123,
          "count": 1960
        },
        {
          "bin": 8,
          "expected": 0.7471448828246803,
          "observed": 0.5463258785942492,
          "count": 939
        },
        {
          "bin": 9,
          "expected": 0.8379285376019578,
          "observed": 0.6109422492401215,
          "count": 329
        },
        {
          "bin": 10,
          "expected": 0.9344488195843506,
          "observed": 0.5365853658536586,
          "count": 41
        }
      ]
    },
    {
      "market": "SOG",
      "line": 2.5,
      "window": 20,
      "count": 30105,
      "accuracy": 0.6975917621657532,
      "brier": 0.20022632178552838,
      "calibration_params": {
        "t": 1.0000000000000002,
        "b": -0.15,
        "brier_post": 0.1972079031664536
      },
      "calibration": [
        {
          "bin": 1,
          "expected": 0.08154648825517888,
          "observed": 0.19982316534040673,
          "count": 1131
        },
        {
          "bin": 2,
          "expected": 0.16247340746313316,
          "observed": 0.15294117647058825,
          "count": 4420
        },
        {
          "bin": 3,
          "expected": 0.24898789240377467,
          "observed": 0.20576368876080692,
          "count": 6940
        },
        {
          "bin": 4,
          "expected": 0.34448345902588917,
          "observed": 0.28165374677002586,
          "count": 6966
        },
        {
          "bin": 5,
          "expected": 0.4474661200107558,
          "observed": 0.3746448087431694,
          "count": 4575
        },
        {
          "bin": 6,
          "expected": 0.5484510097082773,
          "observed": 0.43107546048722517,
          "count": 3366
        },
        {
          "bin": 7,
          "expected": 0.6439508426651248,
          "observed": 0.5408608858390518,
          "count": 1603
        },
        {
          "bin": 8,
          "expected": 0.7454485932179188,
          "observed": 0.5783132530120482,
          "count": 830
        },
        {
          "bin": 9,
          "expected": 0.8397497102014754,
          "observed": 0.6639344262295082,
          "count": 244
        },
        {
          "bin": 10,
          "expected": 0.9405320241564918,
          "observed": 0.5,
          "count": 30
        }
      ]
    },
    {
      "market": "SOG",
      "line": 3.5,
      "window": 5,
      "count": 29990,
      "accuracy": 0.8395798599533177,
      "brier": 0.12453084617975543,
      "calibration_params": {
        "t": 0.9500000000000002,
        "b": -0.15,
        "brier_post": 0.12138221975348928
      },
      "calibration": [
        {
          "bin": 1,
          "expected": 0.04878172324462829,
          "observed": 0.07039241212572066,
          "count": 10754
        },
        {
          "bin": 2,
          "expected": 0.14267281475094193,
          "observed": 0.12220902612826604,
          "count": 8420
        },
        {
          "bin": 3,
          "expected": 0.24805309997751765,
          "observed": 0.1693548387096774,
          "count": 4588
        },
        {
          "bin": 4,
          "expected": 0.3499387037646599,
          "observed": 0.22581779810059796,
          "count": 2843
        },
        {
          "bin": 5,
          "expected": 0.44933165963347876,
          "observed": 0.259010384850336,
          "count": 1637
        },
        {
          "bin": 6,
          "expected": 0.5462304429464849,
          "observed": 0.2904608788853162,
          "count": 933
        },
        {
          "bin": 7,
          "expected": 0.6366827176843857,
          "observed": 0.341747572815534,
          "count": 515
        },
        {
          "bin": 8,
          "expected": 0.7419428816701508,
          "observed": 0.3964757709251101,
          "count": 227
        },
        {
          "bin": 9,
          "expected": 0.8389161581203117,
          "observed": 0.4375,
          "count": 64
        },
        {
          "bin": 10,
          "expected": 0.9226107286722827,
          "observed": 0.1111111111111111,
          "count": 9
        }
      ]
    },
    {
      "market": "SOG",
      "line": 3.5,
      "window": 10,
      "count": 30098,
      "accuracy": 0.8505548541431325,
      "brier": 0.11840901169785509,
      "calibration_params": {
        "t": 0.9000000000000001,
        "b": -0.15,
        "brier_post": 0.11573978730387076
      },
      "calibration": [
        {
          "bin": 1,
          "expected": 0.05655377113647293,
          "observed": 0.06207935710698142,
          "count": 9955
        },
        {
          "bin": 2,
          "expected": 0.14391341492374063,
          "observed": 0.11424,
          "count": 9375
        },
        {
          "bin": 3,
          "expected": 0.2437947841602907,
          "observed": 0.173698738170347,
          "count": 5072
        },
        {
          "bin": 4,
          "expected": 0.34499877297419845,
          "observed": 0.23783599863899285,
          "count": 2939
        },
        {
          "bin": 5,
          "expected": 0.4431372678516021,
          "observed": 0.30764290301862557,
          "count": 1557
        },
        {
          "bin": 6,
          "expected": 0.5485354507673185,
          "observed": 0.348993288590604,
          "count": 745
        },
        {
          "bin": 7,
          "expected": 0.6392294539938862,
          "observed": 0.4405144694533762,
          "count": 311
        },
        {
          "bin": 8,
          "expected": 0.7368616553761816,
          "observed": 0.38392857142857145,
          "count": 112
        },
        {
          "bin": 9,
          "expected": 0.8399765666943199,
          "observed": 0.36,
          "count": 25
        },
        {
          "bin": 10,
          "expected": 0.9238610557914267,
          "observed": 0.14285714285714285,
          "count": 7
        }
      ]
    },
    {
      "market": "SOG",
      "line": 3.5,
      "window": 20,
      "count": 30105,
      "accuracy": 0.8535459226042186,
      "brier": 0.11590080177525543,
      "calibration_params": {
        "t": 0.9000000000000001,
        "b": -0.15,
        "brier_post": 0.1135722487361094
      },
      "calibration": [
        {
          "bin": 1,
          "expected": 0.06116758907100536,
          "observed": 0.05742915634091154,
          "count": 9281
        },
        {
          "bin": 2,
          "expected": 0.14462414913231125,
          "observed": 0.10713942538675891,
          "count": 10407
        },
        {
          "bin": 3,
          "expected": 0.24566245661864322,
          "observed": 0.1913604378420641,
          "count": 5116
        },
        {
          "bin": 4,
          "expected": 0.3440226523095777,
          "observed": 0.2519607843137255,
          "count": 3060
        },
        {
          "bin": 5,
          "expected": 0.4434028670928533,
          "observed": 0.3271555197421434,
          "count": 1241
        },
        {
          "bin": 6,
          "expected": 0.5484368157706824,
          "observed": 0.3699851411589896,
          "count": 673
        },
        {
          "bin": 7,
          "expected": 0.6406923703998844,
          "observed": 0.48826291079812206,
          "count": 213
        },
        {
          "bin": 8,
          "expected": 0.7366175124889766,
          "observed": 0.39325842696629215,
          "count": 89
        },
        {
          "bin": 9,
          "expected": 0.8456819361042114,
          "observed": 0.3333333333333333,
          "count": 18
        },
        {
          "bin": 10,
          "expected": 0.9238610557914267,
          "observed": 0.14285714285714285,
          "count": 7
        }
      ]
    }
  ]
}