{
  "ml_home": {
    "team:CBJ": 0.04706,
    "div:Metropolitan": 0.02622,
    "conf:East": 0.02622,
    "team:MTL": -0.05,
    "div:Atlantic": -0.05,
    "team:CAR": -0.05,
    "team:ANA": 0.05,
    "div:Pacific": 0.01767,
    "conf:West": 0.05,
    "team:NYR": -0.05,
    "team:DET": 0.045197,
    "team:BUF": 0.044293,
    "team:NJD": -0.04802,
    "team:TOR": -0.049,
    "team:DAL": 0.05,
    "div:Central": 0.05,
    "team:WPG": 0.04802,
    "team:NSH": 0.045197,
    "team:CGY": 0.049,
    "team:VGK": 0.045197,
    "team:EDM": 0.049,
    "team:VAN": 0.049,
    "team:WSH": 0.05,
    "team:MIN": -0.042539,
    "team:TBL": -0.049,
    "team:PIT": -0.042539,
    "team:NYI": 0.04706,
    "team:SJS": -0.025964,
    "team:PHI": -0.03671,
    "team:LAK": 0.026578,
    "team:STL": -0.036072,
    "team:COL": 0.045197,
    "team:SEA": -0.049,
    "team:UTA": -0.040854,
    "team:CHI": 0.043407,
    "team:BOS": 0.049,
    "team:FLA": 0.05,
    "team:OTT": -0.049
  },
  "goals": {
    "team:CBJ": -0.3,
    "div:Metropolitan": -0.3,
    "conf:East": -0.3,
    "team:BUF": -0.28812,
    "div:Atlantic": 0.1036,
    "team:MTL": -0.248,
    "team:PIT": 0.0131,
    "team:CAR": -0.1776,
    "team:TBL": -0.294,
    "team:ANA": 0.3,
    "div:Pacific": 0.3,
    "conf:West": -0.1728,
    "team:UTA": -0.294,
    "div:Central": -0.3,
    "team:NYR": -0.3,
    "team:BOS": 0.294,
    "team:DET": 0.294,
    "team:CHI": -0.3,
    "team:NJD": -0.294,
    "team:NYI": -0.3,
    "team:TOR": -0.179046,
    "team:OTT": -0.294,
    "team:PHI": -0.0317,
    "team:DAL": 0.1293,
    "team:MIN": -0.294,
    "team:WPG": -0.243334,
    "team:EDM": 0.294,
    "team:NSH": -0.0,
    "team:CGY": -0.241962,
    "team:SEA": -0.03577,
    "team:VGK": 0.0615,
    "team:LAK": 0.294,
    "team:FLA": 0.3,
    "team:VAN": -0.047432,
    "team:WSH": -0.0467,
    "team:SJS": -0.0433,
    "team:STL": -0.048,
    "team:COL": 0.0666
  }
}