{
  "data": {
    "games": {
      "edges": {
        "count": 48,
        "rows": [
          {
            "away": "Dallas Stars",
            "bet": "over",
            "book": null,
            "edge_reasons": "total 6.66 vs line 5.5 (+1.16); p=0.645; P1 pace 2.10",
            "edge_score": 0.5970927755165713,
            "ev": 0.1615999999999999,
            "home": "New York Islanders",
            "market": "ev_over",
            "market_group": "totals",
            "price": -125.0,
            "prob": 0.6453333333333333,
            "side": "Over 5.5",
            "totals_line": 5.5
          },
          {
            "away": "Chicago Blackhawks",
            "bet": "over",
            "book": null,
            "edge_reasons": "total 6.59 vs line 5.5 (+1.09); p=0.639; P1 pace 2.08",
            "edge_score": 0.5845723018472277,
            "ev": 0.1711944444444446,
            "home": "Philadelphia Flyers",
            "market": "ev_over",
            "market_group": "totals",
            "price": -120.0,
            "prob": 0.6388333333333334,
            "side": "Over 5.5",
            "totals_line": 5.5
          },
          {
            "away": "Minnesota Wild",
            "bet": "under",
            "book": null,
            "edge_reasons": "total 5.72 vs line 6.5 (-0.78); p=0.640; P1 pace 1.84",
            "edge_score": 0.5781269251292099,
            "ev": 0.1727222222222224,
            "home": "Florida Panthers",
            "market": "ev_under",
            "market_group": "totals",
            "price": -120.0,
            "prob": 0.6396666666666667,
            "side": "Under 6.5",
            "totals_line": 6.5
          },
          {
            "away": "Washington Capitals",
            "bet": "over",
            "book": null,
            "edge_reasons": "total 6.46 vs line 5.5 (+0.96); p=0.617; P1 pace 2.02",
            "edge_score": 0.5458623570692505,
            "ev": 0.091025641025641,
            "home": "Utah Mammoth",
            "market": "ev_over",
            "market_group": "totals",
            "price": -130.0,
            "prob": 0.6166666666666667,
            "side": "Over 5.5",
            "totals_line": 5.5
          },
          {
            "away": "New Jersey Devils",
            "bet": "over",
            "book": null,
            "edge_reasons": "total 6.45 vs line 5.5 (+0.95); p=0.613; P1 pace 2.04",
            "edge_score": 0.545774192534165,
            "ev": 0.0676543209876542,
            "home": "Nashville Predators",
            "market": "ev_over",
            "market_group": "totals",
            "price": -135.0,
            "prob": 0.6133333333333333,
            "side": "Over 5.5",
            "totals_line": 5.5
          },
          {
            "away": "Columbus Blue Jackets",
            "bet": "under",
            "book": null,
            "edge_reasons": "total 6.09 vs line 6.5 (-0.41); p=0.584; P1 pace 1.95",
            "edge_score": 0.4539889312488731,
            "ev": 0.1139545454545455,
            "home": "Montréal Canadiens",
            "market": "ev_under",
            "market_group": "totals",
            "price": -110.0,
            "prob": 0.5835,
            "side": "Under 6.5",
            "totals_line": 6.5
          },
          {
            "away": "Pittsburgh Penguins",
            "bet": "over",
            "book": null,
            "edge_reasons": "total 6.04 vs line 5.5 (+0.54); p=0.548; P1 pace 1.91",
            "edge_score": 0.4187804595736994,
            "ev": -0.0301666666666666,
            "home": "Ottawa Senators",
            "market": "ev_over",
            "market_group": "totals",
            "price": -130.0,
            "prob": 0.5481666666666667,
            "side": "Over 5.5",
            "totals_line": 5.5
          },
          {
            "away": "Edmonton Oilers",
            "bet": "under",
            "book": null,
            "edge_reasons": "total 6.22 vs line 6.5 (-0.28); p=0.564; P1 pace 1.96",
            "edge_score": 0.4077588391575982,
            "ev": 0.0773636363636364,
            "home": "Vegas Golden Knights",
            "market": "ev_under",
            "market_group": "totals",
            "price": -110.0,
            "prob": 0.5643333333333334,
            "side": "Under 6.5",
            "totals_line": 6.5
          },
          {
            "away": "Anaheim Ducks",
            "bet": "over",
            "book": null,
            "edge_reasons": "total 6.53 vs line 6.5 (+0.03); p=0.485; P1 pace 2.10",
            "edge_score": 0.3154406288334268,
            "ev": -0.0744090909090908,
            "home": "Calgary Flames",
            "market": "ev_over",
            "market_group": "totals",
            "price": -110.0,
            "prob": 0.4848333333333333,
            "side": "Over 6.5",
            "totals_line": 6.5
          },
          {
            "away": "Los Angeles Kings",
            "bet": "over",
            "book": null,
            "edge_reasons": "total 5.76 vs line 5.5 (+0.26); p=0.503; P1 pace 1.81",
            "edge_score": 0.3070350892882337,
            "ev": -0.1103717948717948,
            "home": "Vancouver Canucks",
            "market": "ev_over",
            "market_group": "totals",
            "price": -130.0,
            "prob": 0.5028333333333334,
            "side": "Over 5.5",
            "totals_line": 5.5
          },
          {
            "away": "Colorado Avalanche",
            "bet": "under",
            "book": null,
            "edge_reasons": "total 6.46 vs line 6.5 (-0.04); p=0.527; P1 pace 2.04",
            "edge_score": 0.3020559480299242,
            "ev": -0.0510999999999999,
            "home": "Winnipeg Jets",
            "market": "ev_under",
            "market_group": "totals",
            "price": -125.0,
            "prob": 0.5271666666666667,
            "side": "Under 6.5",
            "totals_line": 6.5
          },
          {
            "away": "Seattle Kraken",
            "bet": "under",
            "book": null,
            "edge_reasons": "total 6.45 vs line 6.5 (-0.05); p=0.525; P1 pace 2.06",
            "edge_score": 0.30056852005785,
            "ev": -0.0702692307692308,
            "home": "Tampa Bay Lightning",
            "market": "ev_under",
            "market_group": "totals",
            "price": -130.0,
            "prob": 0.5255,
            "side": "Under 6.5",
            "totals_line": 6.5
          },
          {
            "away": "Colorado Avalanche",
            "bet": "over",
            "book": null,
            "edge_reasons": "total 6.46 vs line 6.5 (-0.04); p=0.473; P1 pace 2.04",
            "edge_score": 0.2994656205975267,
            "ev": -0.0306916666666667,
            "home": "Winnipeg Jets",
            "market": "ev_over",
            "market_group": "totals",
            "price": 105.0,
            "prob": 0.4728333333333333,
            "side": "Over 6.5",
            "totals_line": 6.5
          },
          {
            "away": "Seattle Kraken",
            "bet": "over",
            "book": null,
            "edge_reasons": "total 6.45 vs line 6.5 (-0.05); p=0.474; P1 pace 2.06",
            "edge_score": 0.2979726564127382,
            "ev": -0.00355,
            "home": "Tampa Bay Lightning",
            "market": "ev_over",
            "market_group": "totals",
            "price": 110.0,
            "prob": 0.4745,
            "side": "Over 6.5",
            "totals_line": 6.5
          },
          {
            "away": "Minnesota Wild",
            "bet": "away_ml",
            "book": null,
            "edge_reasons": "p=0.634",
            "edge_score": 0.2684999999999999,
            "ev": 0.0627972972972972,
            "home": "Florida Panthers",
            "market": "ev_away_ml",
            "market_group": "moneyline",
            "price": -148.0,
            "prob": 0.63425,
            "side": "Minnesota Wild",
            "totals_line": null
          },
          {
            "away": "Minnesota Wild",
            "bet": "home_ml",
            "book": null,
            "edge_reasons": "p=0.366",
            "edge_score": 0.2684999999999999,
            "ev": -0.1807199999999998,
            "home": "Florida Panthers",
            "market": "ev_home_ml",
            "market_group": "moneyline",
            "price": 124.0,
            "prob": 0.36575,
            "side": "Florida Panthers",
            "totals_line": null
          },
          {
            "away": "Anaheim Ducks",
            "bet": "under",
            "book": null,
            "edge_reasons": "total 6.53 vs line 6.5 (+0.03); p=0.515; P1 pace 2.10",
            "edge_score": 0.2646221162646125,
            "ev": -0.0164999999999999,
            "home": "Calgary Flames",
            "market": "ev_under",
            "market_group": "totals",
            "price": -110.0,
            "prob": 0.5151666666666667,
            "side": "Under 6.5",
            "totals_line": 6.5
          },
          {
            "away": "Edmonton Oilers",
            "bet": "over",
            "book": null,
            "edge_reasons": "total 6.22 vs line 6.5 (-0.28); p=0.436; P1 pace 1.96",
            "edge_score": 0.2602254745678921,
            "ev": -0.1682727272727273,
            "home": "Vegas Golden Knights",
            "market": "ev_over",
            "market_group": "totals",
            "price": -110.0,
            "prob": 0.4356666666666666,
            "side": "Over 6.5",
            "totals_line": 6.5
          },
          {
            "away": "Los Angeles Kings",
            "bet": "under",
            "book": null,
            "edge_reasons": "total 5.76 vs line 5.5 (+0.26); p=0.497; P1 pace 1.81",
            "edge_score": 0.2509727538490212,
            "ev": 0.04405,
            "home": "Vancouver Canucks",
            "market": "ev_under",
            "market_group": "totals",
            "price": 110.0,
            "prob": 0.4971666666666666,
            "side": "Under 5.5",
            "totals_line": 5.5
          },
          {
            "away": "Columbus Blue Jackets",
            "bet": "over",
            "book": null,
            "edge_reasons": "total 6.09 vs line 6.5 (-0.41); p=0.416; P1 pace 1.95",
            "edge_score": 0.2482698922805386,
            "ev": -0.2048636363636363,
            "home": "Montréal Canadiens",
            "market": "ev_over",
            "market_group": "totals",
            "price": -110.0,
            "prob": 0.4165,
            "side": "Over 6.5",
            "totals_line": 6.5
          },
          {
            "away": "Minnesota Wild",
            "bet": "over",
            "book": null,
            "edge_reasons": "total 5.72 vs line 6.5 (-0.78); p=0.360; P1 pace 1.84",
            "edge_score": 0.2245711140864764,
            "ev": -0.2793333333333332,
            "home": "Florida Panthers",
            "market": "ev_over",
            "market_group": "totals",
            "price": 100.0,
            "prob": 0.3603333333333333,
            "side": "Over 6.5",
            "totals_line": 6.5
          },
          {
            "away": "Pittsburgh Penguins",
            "bet": "under",
            "book": null,
            "edge_reasons": "total 6.04 vs line 5.5 (+0.54); p=0.452; P1 pace 1.91",
            "edge_score": 0.2202940502302221,
            "ev": -0.05115,
            "home": "Ottawa Senators",
            "market": "ev_under",
            "market_group": "totals",
            "price": 110.0,
            "prob": 0.4518333333333333,
            "side": "Under 5.5",
            "totals_line": 5.5
          },
          {
            "away": "Chicago Blackhawks",
            "bet": "under",
            "book": null,
            "edge_reasons": "total 6.59 vs line 5.5 (+1.09); p=0.361; P1 pace 2.08",
            "edge_score": 0.2166355412900272,
            "ev": -0.2776666666666667,
            "home": "Philadelphia Flyers",
            "market": "ev_under",
            "market_group": "totals",
            "price": 100.0,
            "prob": 0.3611666666666667,
            "side": "Under 5.5",
            "totals_line": 5.5
          },
          {
            "away": "Dallas Stars",
            "bet": "under",
            "book": null,
            "edge_reasons": "total 6.66 vs line 5.5 (+1.16); p=0.355; P1 pace 2.10",
            "edge_score": 0.2157385970324483,
            "ev": -0.2729333333333333,
            "home": "New York Islanders",
            "market": "ev_under",
            "market_group": "totals",
            "price": 105.0,
            "prob": 0.3546666666666667,
            "side": "Under 5.5",
            "totals_line": 5.5
          },
          {
            "away": "Washington Capitals",
            "bet": "under",
            "book": null,
            "edge_reasons": "total 6.46 vs line 5.5 (+0.96); p=0.383; P1 pace 2.02",
            "edge_score": 0.2157062703817299,
            "ev": -0.1949999999999999,
            "home": "Utah Mammoth",
            "market": "ev_under",
            "market_group": "totals",
            "price": 110.0,
            "prob": 0.3833333333333333,
            "side": "Under 5.5",
            "totals_line": 5.5
          },
          {
            "away": "New Jersey Devils",
            "bet": "under",
            "book": null,
            "edge_reasons": "total 6.45 vs line 5.5 (+0.95); p=0.387; P1 pace 2.04",
            "edge_score": 0.2098336506030897,
            "ev": -0.1725333333333334,
            "home": "Nashville Predators",
            "market": "ev_under",
            "market_group": "totals",
            "price": 114.0,
            "prob": 0.3866666666666666,
            "side": "Under 5.5",
            "totals_line": 5.5
          },
          {
            "away": "Edmonton Oilers",
            "bet": "home_ml",
            "book": null,
            "edge_reasons": "p=0.569",
            "edge_score": 0.137,
            "ev": -0.0103888888888888,
            "home": "Vegas Golden Knights",
            "market": "ev_home_ml",
            "market_group": "moneyline",
            "price": -135.0,
            "prob": 0.5685,
            "side": "Vegas Golden Knights",
            "totals_line": null
          },
          {
            "away": "Edmonton Oilers",
            "bet": "away_ml",
            "book": null,
            "edge_reasons": "p=0.431",
            "edge_score": 0.137,
            "ev": -0.0765900000000001,
            "home": "Vegas Golden Knights",
            "market": "ev_away_ml",
            "market_group": "moneyline",
            "price": 114.0,
            "prob": 0.4315,
            "side": "Edmonton Oilers",
            "totals_line": null
          },
          {
            "away": "Columbus Blue Jackets",
            "bet": "away_ml",
            "book": null,
            "edge_reasons": "p=0.560",
            "edge_score": 0.1193333333333332,
            "ev": 0.1193333333333332,
            "home": "Montréal Canadiens",
            "market": "ev_away_ml",
            "market_group": "moneyline",
            "price": 100.0,
            "prob": 0.5596666666666666,
            "side": "Columbus Blue Jackets",
            "totals_line": null
          },
          {
            "away": "Columbus Blue Jackets",
            "bet": "home_ml",
            "book": null,
            "edge_reasons": "p=0.440",
            "edge_score": 0.1193333333333332,
            "ev": -0.1927222222222221,
            "home": "Montréal Canadiens",
            "market": "ev_home_ml",
            "market_group": "moneyline",
            "price": -120.0,
            "prob": 0.4403333333333333,
            "side": "Montréal Canadiens",
            "totals_line": null
          },
          {
            "away": "New Jersey Devils",
            "bet": "home_ml",
            "book": null,
            "edge_reasons": "p=0.463",
            "edge_score": 0.0735,
            "ev": -0.1507083333333333,
            "home": "Nashville Predators",
            "market": "ev_home_ml",
            "market_group": "moneyline",
            "price": -120.0,
            "prob": 0.46325,
            "side": "Nashville Predators",
            "totals_line": null
          },
          {
            "away": "New Jersey Devils",
            "bet": "away_ml",
            "book": null,
            "edge_reasons": "p=0.537",
            "edge_score": 0.0734999999999999,
            "ev": 0.0734999999999999,
            "home": "Nashville Predators",
            "market": "ev_away_ml",
            "market_group": "moneyline",
            "price": 100.0,
            "prob": 0.53675,
            "side": "New Jersey Devils",
            "totals_line": null
          },
          {
            "away": "Anaheim Ducks",
            "bet": "away_ml",
            "book": null,
            "edge_reasons": "p=0.464",
            "edge_score": 0.0713333333333333,
            "ev": -0.221927927927928,
            "home": "Calgary Flames",
            "market": "ev_away_ml",
            "market_group": "moneyline",
            "price": -148.0,
            "prob": 0.4643333333333333,
            "side": "Anaheim Ducks",
            "totals_line": null
          },
          {
            "away": "Anaheim Ducks",
            "bet": "home_ml",
            "book": null,
            "edge_reasons": "p=0.536",
            "edge_score": 0.0713333333333332,
            "ev": 0.1998933333333333,
            "home": "Calgary Flames",
            "market": "ev_home_ml",
            "market_group": "moneyline",
            "price": 124.0,
            "prob": 0.5356666666666666,
            "side": "Calgary Flames",
            "totals_line": null
          },
          {
            "away": "Chicago Blackhawks",
            "bet": "away_ml",
            "book": null,
            "edge_reasons": "p=0.532",
            "edge_score": 0.0649999999999999,
            "ev": 0.2567000000000001,
            "home": "Philadelphia Flyers",
            "market": "ev_away_ml",
            "market_group": "moneyline",
            "price": 136.0,
            "prob": 0.5325,
            "side": "Chicago Blackhawks",
            "totals_line": null
          },
          {
            "away": "Chicago Blackhawks",
            "bet": "home_ml",
            "book": null,
            "edge_reasons": "p=0.468",
            "edge_score": 0.0649999999999999,
            "ev": -0.2439197530864196,
            "home": "Philadelphia Flyers",
            "market": "ev_home_ml",
            "market_group": "moneyline",
            "price": -162.0,
            "prob": 0.4675,
            "side": "Philadelphia Flyers",
            "totals_line": null
          },
          {
            "away": "Seattle Kraken",
            "bet": "away_ml",
            "book": null,
            "edge_reasons": "p=0.528",
            "edge_score": 0.0555000000000001,
            "ev": 0.6624125000000002,
            "home": "Tampa Bay Lightning",
            "market": "ev_away_ml",
            "market_group": "moneyline",
            "price": 215.0,
            "prob": 0.52775,
            "side": "Seattle Kraken",
            "totals_line": null
          },
          {
            "away": "Seattle Kraken",
            "bet": "home_ml",
            "book": null,
            "edge_reasons": "p=0.472",
            "edge_score": 0.0554999999999999,
            "ev": -0.3495424528301887,
            "home": "Tampa Bay Lightning",
            "market": "ev_home_ml",
            "market_group": "moneyline",
            "price": -265.0,
            "prob": 0.47225,
            "side": "Tampa Bay Lightning",
            "totals_line": null
          },
          {
            "away": "Los Angeles Kings",
            "bet": "home_ml",
            "book": null,
            "edge_reasons": "p=0.527",
            "edge_score": 0.0536666666666667,
            "ev": 0.2907416666666669,
            "home": "Vancouver Canucks",
            "market": "ev_home_ml",
            "market_group": "moneyline",
            "price": 145.0,
            "prob": 0.5268333333333334,
            "side": "Vancouver Canucks",
            "totals_line": null
          },
          {
            "away": "Los Angeles Kings",
            "bet": "away_ml",
            "book": null,
            "edge_reasons": "p=0.473",
            "edge_score": 0.0536666666666666,
            "ev": -0.2564523809523809,
            "home": "Vancouver Canucks",
            "market": "ev_away_ml",
            "market_group": "moneyline",
            "price": -175.0,
            "prob": 0.4731666666666667,
            "side": "Los Angeles Kings",
            "totals_line": null
          },
          {
            "away": "Washington Capitals",
            "bet": "away_ml",
            "book": null,
            "edge_reasons": "p=0.523",
            "edge_score": 0.0461666666666666,
            "ev": 0.2030916666666665,
            "home": "Utah Mammoth",
            "market": "ev_away_ml",
            "market_group": "moneyline",
            "price": 130.0,
            "prob": 0.5230833333333333,
            "side": "Washington Capitals",
            "totals_line": null
          },
          {
            "away": "Washington Capitals",
            "bet": "home_ml",
            "book": null,
            "edge_reasons": "p=0.477",
            "edge_score": 0.0461666666666666,
            "ev": -0.2153951612903226,
            "home": "Utah Mammoth",
            "market": "ev_home_ml",
            "market_group": "moneyline",
            "price": -155.0,
            "prob": 0.4769166666666666,
            "side": "Utah Mammoth",
            "totals_line": null
          },
          {
            "away": "Pittsburgh Penguins",
            "bet": "home_ml",
            "book": null,
            "edge_reasons": "p=0.482",
            "edge_score": 0.0368333333333333,
            "ev": -0.1616882716049383,
            "home": "Ottawa Senators",
            "market": "ev_home_ml",
            "market_group": "moneyline",
            "price": -135.0,
            "prob": 0.4815833333333333,
            "side": "Ottawa Senators",
            "totals_line": null
          },
          {
            "away": "Pittsburgh Penguins",
            "bet": "away_ml",
            "book": null,
            "edge_reasons": "p=0.518",
            "edge_score": 0.0368333333333332,
            "ev": 0.1094116666666664,
            "home": "Ottawa Senators",
            "market": "ev_away_ml",
            "market_group": "moneyline",
            "price": 114.0,
            "prob": 0.5184166666666666,
            "side": "Pittsburgh Penguins",
            "totals_line": null
          },
          {
            "away": "Dallas Stars",
            "bet": "home_ml",
            "book": null,
            "edge_reasons": "p=0.486",
            "edge_score": 0.0283333333333333,
            "ev": 0.0202500000000001,
            "home": "New York Islanders",
            "market": "ev_home_ml",
            "market_group": "moneyline",
            "price": 110.0,
            "prob": 0.4858333333333333,
            "side": "New York Islanders",
            "totals_line": null
          },
          {
            "away": "Dallas Stars",
            "bet": "away_ml",
            "book": null,
            "edge_reasons": "p=0.514",
            "edge_score": 0.0283333333333333,
            "ev": -0.0903205128205128,
            "home": "New York Islanders",
            "market": "ev_away_ml",
            "market_group": "moneyline",
            "price": -130.0,
            "prob": 0.5141666666666667,
            "side": "Dallas Stars",
            "totals_line": null
          },
          {
            "away": "Colorado Avalanche",
            "bet": "home_ml",
            "book": null,
            "edge_reasons": "p=0.488",
            "edge_score": 0.0243333333333333,
            "ev": 0.2390966666666667,
            "home": "Winnipeg Jets",
            "market": "ev_home_ml",
            "market_group": "moneyline",
            "price": 154.0,
            "prob": 0.4878333333333333,
            "side": "Winnipeg Jets",
            "totals_line": null
          },
          {
            "away": "Colorado Avalanche",
            "bet": "away_ml",
            "book": null,
            "edge_reasons": "p=0.512",
            "edge_score": 0.0243333333333333,
            "ev": -0.2109864864864865,
            "home": "Winnipeg Jets",
            "market": "ev_away_ml",
            "market_group": "moneyline",
            "price": -185.0,
            "prob": 0.5121666666666667,
            "side": "Colorado Avalanche",
            "totals_line": null
          }
        ],
        "source": "edges_sim_2026-03-26.csv"
      },
      "predictions": {
        "count": 13,
        "rows": [
          {
            "away": "Anaheim Ducks",
            "away_ml_odds": -148.0,
            "away_pl_+1.5_odds": null,
            "date": "2026-03-26",
            "home": "Calgary Flames",
            "home_ml_odds": 124.0,
            "home_pl_-1.5_odds": null,
            "model_total": 6.526,
            "over_odds": -110.0,
            "p_away_ml": 0.4643333333333333,
            "p_away_pl_+1.5": 0.728,
            "p_home_ml": 0.5356666666666666,
            "p_home_pl_-1.5": 0.272,
            "p_over": 0.4848333333333333,
            "p_under": 0.5151666666666667,
            "pl_line_used": 1.5,
            "proj_away_goals": 3.1585,
            "proj_home_goals": 3.3675,
            "segments": {
              "final": {
                "away_win_prob": 0.38846394180068966,
                "home_win_prob": 0.4511867825941929,
                "tie_prob": 0.16034927560511747
              },
              "ot": {
                "no_prob": 0.8396507243948825,
                "yes_prob": 0.16034927560511747
              },
              "p1": {
                "away_win_prob": 0.33198567360308473,
                "home_win_prob": 0.36852311614272487,
                "tie_prob": 0.2994912102541904
              },
              "p2": {
                "away_win_prob": 0.33116925247496987,
                "home_win_prob": 0.3758403678447881,
                "tie_prob": 0.29299037968024205
              },
              "p3": {
                "away_win_prob": 0.3415032862186323,
                "home_win_prob": 0.3642356425479614,
                "tie_prob": 0.2942610712334062
              }
            },
            "total_line_used": 6.5,
            "under_odds": -110.0
          },
          {
            "away": "Minnesota Wild",
            "away_ml_odds": -148.0,
            "away_pl_+1.5_odds": null,
            "date": "2026-03-26",
            "home": "Florida Panthers",
            "home_ml_odds": 124.0,
            "home_pl_-1.5_odds": null,
            "model_total": 5.715833333333333,
            "over_odds": 100.0,
            "p_away_ml": 0.63425,
            "p_away_pl_+1.5": 0.8733333333333333,
            "p_home_ml": 0.36575,
            "p_home_pl_-1.5": 0.1266666666666666,
            "p_over": 0.3603333333333333,
            "p_under": 0.6396666666666667,
            "pl_line_used": 1.5,
            "proj_away_goals": 3.24,
            "proj_home_goals": 2.4758333333333336,
            "segments": {
              "final": {
                "away_win_prob": 0.540356465657328,
                "home_win_prob": 0.29481473972505545,
                "tie_prob": 0.16482879461761654
              },
              "ot": {
                "no_prob": 0.8351712053823834,
                "yes_prob": 0.16482879461761654
              },
              "p1": {
                "away_win_prob": 0.4148818595113225,
                "home_win_prob": 0.2652394446636856,
                "tie_prob": 0.3198786958249918
              },
              "p2": {
                "away_win_prob": 0.41311878582252204,
                "home_win_prob": 0.27399565178958224,
                "tie_prob": 0.3128855623878957
              },
              "p3": {
                "away_win_prob": 0.3990408653042846,
                "home_win_prob": 0.2812443542098452,
                "tie_prob": 0.31971478048587026
              }
            },
            "total_line_used": 6.5,
            "under_odds": -120.0
          },
          {
            "away": "Columbus Blue Jackets",
            "away_ml_odds": 100.0,
            "away_pl_+1.5_odds": -258.0,
            "date": "2026-03-26",
            "home": "Montréal Canadiens",
            "home_ml_odds": -120.0,
            "home_pl_-1.5_odds": 210.0,
            "model_total": 6.0895,
            "over_odds": -110.0,
            "p_away_ml": 0.5596666666666666,
            "p_away_pl_+1.5": 0.8106666666666666,
            "p_home_ml": 0.4403333333333333,
            "p_home_pl_-1.5": 0.1893333333333333,
            "p_over": 0.4165,
            "p_under": 0.5835,
            "pl_line_used": 1.5,
            "proj_away_goals": 3.1973333333333334,
            "proj_home_goals": 2.8921666666666668,
            "segments": {
              "final": {
                "away_win_prob": 0.4638967589130849,
                "home_win_prob": 0.3702637436774295,
                "tie_prob": 0.16583949740948556
              },
              "ot": {
                "no_prob": 0.8341605025905144,
                "yes_prob": 0.16583949740948556
              },
              "p1": {
                "away_win_prob": 0.3800326715256434,
                "home_win_prob": 0.30809228025930097,
                "tie_prob": 0.31187504821505563
              },
              "p2": {
                "away_win_prob": 0.37328196879656594,
                "home_win_prob": 0.3210198312367967,
                "tie_prob": 0.3056981999666372
              },
              "p3": {
                "away_win_prob": 0.3614641411167202,
                "home_win_prob": 0.33106002842083393,
                "tie_prob": 0.30747583046244586
              }
            },
            "total_line_used": 6.5,
            "under_odds": -110.0
          },
          {
            "away": "New Jersey Devils",
            "away_ml_odds": 100.0,
            "away_pl_+1.5_odds": -265.0,
            "date": "2026-03-26",
            "home": "Nashville Predators",
            "home_ml_odds": -120.0,
            "home_pl_-1.5_odds": 215.0,
            "model_total": 6.448,
            "over_odds": -135.0,
            "p_away_ml": 0.53675,
            "p_away_pl_+1.5": 0.7845,
            "p_home_ml": 0.46325,
            "p_home_pl_-1.5": 0.2155,
            "p_over": 0.6133333333333333,
            "p_under": 0.3866666666666666,
            "pl_line_used": 1.5,
            "proj_away_goals": 3.3131666666666666,
            "proj_home_goals": 3.1348333333333334,
            "segments": {
              "final": {
                "away_win_prob": 0.4459164170738771,
                "home_win_prob": 0.3923411024802305,
                "tie_prob": 0.16174248044589243
              },
              "ot": {
                "no_prob": 0.8382575195541075,
                "yes_prob": 0.16174248044589243
              },
              "p1": {
                "away_win_prob": 0.3659199935533329,
                "home_win_prob": 0.32937930988888253,
                "tie_prob": 0.3047006965577846
              },
              "p2": {
                "away_win_prob": 0.3652242585164788,
                "home_win_prob": 0.339108119488523,
                "tie_prob": 0.29566762199499824
              },
              "p3": {
                "away_win_prob": 0.36562137161068414,
                "home_win_prob": 0.3394672218943371,
                "tie_prob": 0.29491140649497866
              }
            },
            "total_line_used": 5.5,
            "under_odds": 114.0
          },
          {
            "away": "Dallas Stars",
            "away_ml_odds": -130.0,
            "away_pl_+1.5_odds": null,
            "date": "2026-03-26",
            "home": "New York Islanders",
            "home_ml_odds": 110.0,
            "home_pl_-1.5_odds": null,
            "model_total": 6.655833333333334,
            "over_odds": -125.0,
            "p_away_ml": 0.5141666666666667,
            "p_away_pl_+1.5": 0.7686666666666666,
            "p_home_ml": 0.4858333333333333,
            "p_home_pl_-1.5": 0.2313333333333333,
            "p_over": 0.6453333333333333,
            "p_under": 0.3546666666666667,
            "pl_line_used": 1.5,
            "proj_away_goals": 3.3688333333333333,
            "proj_home_goals": 3.287,
            "segments": {
              "final": {
                "away_win_prob": 0.4329493208418771,
                "home_win_prob": 0.40772244038781064,
                "tie_prob": 0.15932823877031235
              },
              "ot": {
                "no_prob": 0.8406717612296877,
                "yes_prob": 0.15932823877031235
              },
              "p1": {
                "away_win_prob": 0.3497546593458114,
                "home_win_prob": 0.3505249052531046,
                "tie_prob": 0.29972043540108406
              },
              "p2": {
                "away_win_prob": 0.3651570350401049,
                "home_win_prob": 0.34605997327098037,
                "tie_prob": 0.2887829916889148
              },
              "p3": {
                "away_win_prob": 0.36662423989485704,
                "home_win_prob": 0.34345912762308145,
                "tie_prob": 0.28991663248206145
              }
            },
            "total_line_used": 5.5,
            "under_odds": 105.0
          },
          {
            "away": "Pittsburgh Penguins",
            "away_ml_odds": 114.0,
            "away_pl_+1.5_odds": -205.0,
            "date": "2026-03-26",
            "home": "Ottawa Senators",
            "home_ml_odds": -135.0,
            "home_pl_-1.5_odds": 170.0,
            "model_total": 6.04,
            "over_odds": -130.0,
            "p_away_ml": 0.5184166666666666,
            "p_away_pl_+1.5": 0.7855,
            "p_home_ml": 0.4815833333333333,
            "p_home_pl_-1.5": 0.2145,
            "p_over": 0.5481666666666667,
            "p_under": 0.4518333333333333,
            "pl_line_used": 1.5,
            "proj_away_goals": 3.0671666666666666,
            "proj_home_goals": 2.972833333333333,
            "segments": {
              "final": {
                "away_win_prob": 0.4310960245437173,
                "home_win_prob": 0.40130803605996984,
                "tie_prob": 0.16759593939631287
              },
              "ot": {
                "no_prob": 0.8324040606036871,
                "yes_prob": 0.16759593939631287
              },
              "p1": {
                "away_win_prob": 0.35264265141714735,
                "home_win_prob": 0.3305085720225225,
                "tie_prob": 0.31684877656033017
              },
              "p2": {
                "away_win_prob": 0.35206121925480993,
                "home_win_prob": 0.3416364801196029,
                "tie_prob": 0.3063023006255872
              },
              "p3": {
                "away_win_prob": 0.3539906663854932,
                "home_win_prob": 0.3373995117777936,
                "tie_prob": 0.30860982183671326
              }
            },
            "total_line_used": 5.5,
            "under_odds": 110.0
          },
          {
            "away": "Chicago Blackhawks",
            "away_ml_odds": 136.0,
            "away_pl_+1.5_odds": -185.0,
            "date": "2026-03-26",
            "home": "Philadelphia Flyers",
            "home_ml_odds": -162.0,
            "home_pl_-1.5_odds": 154.0,
            "model_total": 6.5888333333333335,
            "over_odds": -120.0,
            "p_away_ml": 0.5325,
            "p_away_pl_+1.5": 0.7795,
            "p_home_ml": 0.4675,
            "p_home_pl_-1.5": 0.2205,
            "p_over": 0.6388333333333334,
            "p_under": 0.3611666666666667,
            "pl_line_used": 1.5,
            "proj_away_goals": 3.3866666666666667,
            "proj_home_goals": 3.202166666666667,
            "segments": {
              "final": {
                "away_win_prob": 0.4475777052432088,
                "home_win_prob": 0.39248860377638173,
                "tie_prob": 0.15993369098040952
              },
              "ot": {
                "no_prob": 0.8400663090195905,
                "yes_prob": 0.15993369098040952
              },
              "p1": {
                "away_win_prob": 0.3645525526984988,
                "home_win_prob": 0.3342303333535615,
                "tie_prob": 0.3012171139479397
              },
              "p2": {
                "away_win_prob": 0.37334658095526213,
                "home_win_prob": 0.3373488492204665,
                "tie_prob": 0.28930456982427155
              },
              "p3": {
                "away_win_prob": 0.3658383731052363,
                "home_win_prob": 0.34088206909173707,
                "tie_prob": 0.29327955780302656
              }
            },
            "total_line_used": 5.5,
            "under_odds": 100.0
          },
          {
            "away": "San Jose Sharks",
            "away_ml_odds": null,
            "away_pl_+1.5_odds": null,
            "date": "2026-03-26",
            "home": "St. Louis Blues",
            "home_ml_odds": null,
            "home_pl_-1.5_odds": null,
            "model_total": 6.098,
            "over_odds": null,
            "p_away_ml": 0.4709166666666666,
            "p_away_pl_+1.5": 0.7521666666666667,
            "p_home_ml": 0.5290833333333333,
            "p_home_pl_-1.5": 0.2478333333333333,
            "p_over": 0.4188333333333333,
            "p_under": 0.4398333333333333,
            "pl_line_used": 1.5,
            "proj_away_goals": 2.9816666666666665,
            "proj_home_goals": 3.1163333333333334,
            "segments": {
              "final": {
                "away_win_prob": 0.39662122627068486,
                "home_win_prob": 0.43688364853721,
                "tie_prob": 0.16649512519210508
              },
              "ot": {
                "no_prob": 0.8335048748078949,
                "yes_prob": 0.16649512519210508
              },
              "p1": {
                "away_win_prob": 0.3256077340084089,
                "home_win_prob": 0.36222635986143326,
                "tie_prob": 0.3121659061301578
              },
              "p2": {
                "away_win_prob": 0.34240643673899407,
                "home_win_prob": 0.3514381879262144,
                "tie_prob": 0.3061553753347916
              },
              "p3": {
                "away_win_prob": 0.3362810476022661,
                "home_win_prob": 0.35714489524743986,
                "tie_prob": 0.30657405715029395
              }
            },
            "total_line_used": 6.0,
            "under_odds": null
          },
          {
            "away": "Seattle Kraken",
            "away_ml_odds": 215.0,
            "away_pl_+1.5_odds": -115.0,
            "date": "2026-03-26",
            "home": "Tampa Bay Lightning",
            "home_ml_odds": -265.0,
            "home_pl_-1.5_odds": -105.0,
            "model_total": 6.450333333333333,
            "over_odds": 110.0,
            "p_away_ml": 0.52775,
            "p_away_pl_+1.5": 0.785,
            "p_home_ml": 0.47225,
            "p_home_pl_-1.5": 0.215,
            "p_over": 0.4745,
            "p_under": 0.5255,
            "pl_line_used": 1.5,
            "proj_away_goals": 3.2996666666666665,
            "proj_home_goals": 3.1506666666666665,
            "segments": {
              "final": {
                "away_win_prob": 0.44136477359600995,
                "home_win_prob": 0.39688118508064435,
                "tie_prob": 0.1617540413233457
              },
              "ot": {
                "no_prob": 0.8382459586766543,
                "yes_prob": 0.1617540413233457
              },
              "p1": {
                "away_win_prob": 0.364363563982604,
                "home_win_prob": 0.3325294588462612,
                "tie_prob": 0.3031069771711348
              },
              "p2": {
                "away_win_prob": 0.36612555756541965,
                "home_win_prob": 0.33913571829009004,
                "tie_prob": 0.29473872414449037
              },
              "p3": {
                "away_win_prob": 0.35901332801837493,
                "home_win_prob": 0.34413508044475344,
                "tie_prob": 0.2968515915368716
              }
            },
            "total_line_used": 6.5,
            "under_odds": -130.0
          },
          {
            "away": "Washington Capitals",
            "away_ml_odds": 130.0,
            "away_pl_+1.5_odds": -198.0,
            "date": "2026-03-26",
            "home": "Utah Mammoth",
            "home_ml_odds": -155.0,
            "home_pl_-1.5_odds": 164.0,
            "model_total": 6.4625,
            "over_odds": -130.0,
            "p_away_ml": 0.5230833333333333,
            "p_away_pl_+1.5": 0.7746666666666666,
            "p_home_ml": 0.4769166666666666,
            "p_home_pl_-1.5": 0.2253333333333333,
            "p_over": 0.6166666666666667,
            "p_under": 0.3833333333333333,
            "pl_line_used": 1.5,
            "proj_away_goals": 3.2881666666666667,
            "proj_home_goals": 3.174333333333333,
            "segments": {
              "final": {
                "away_win_prob": 0.43644504175222854,
                "home_win_prob": 0.401889858453246,
                "tie_prob": 0.1616650997945255
              },
              "ot": {
                "no_prob": 0.8383349002054745,
                "yes_prob": 0.1616650997945255
              },
              "p1": {
                "away_win_prob": 0.3624067968730584,
                "home_win_prob": 0.3310197187608902,
                "tie_prob": 0.30657348436605136
              },
              "p2": {
                "away_win_prob": 0.35953591103785165,
                "home_win_prob": 0.34826899074059453,
                "tie_prob": 0.2921950982215539
              },
              "p3": {
                "away_win_prob": 0.3598366933576629,
                "home_win_prob": 0.34493034996795596,
                "tie_prob": 0.2952329566743812
              }
            },
            "total_line_used": 5.5,
            "under_odds": 110.0
          },
          {
            "away": "Los Angeles Kings",
            "away_ml_odds": -175.0,
            "away_pl_+1.5_odds": null,
            "date": "2026-03-26",
            "home": "Vancouver Canucks",
            "home_ml_odds": 145.0,
            "home_pl_-1.5_odds": null,
            "model_total": 5.759833333333333,
            "over_odds": -130.0,
            "p_away_ml": 0.4731666666666667,
            "p_away_pl_+1.5": 0.7466666666666666,
            "p_home_ml": 0.5268333333333334,
            "p_home_pl_-1.5": 0.2533333333333333,
            "p_over": 0.5028333333333334,
            "p_under": 0.4971666666666666,
            "pl_line_used": 1.5,
            "proj_away_goals": 2.7955,
            "proj_home_goals": 2.9643333333333333,
            "segments": {
              "final": {
                "away_win_prob": 0.3850723649327706,
                "home_win_prob": 0.443319423569047,
                "tie_prob": 0.17160821149818237
              },
              "ot": {
                "no_prob": 0.8283917885018176,
                "yes_prob": 0.17160821149818237
              },
              "p1": {
                "away_win_prob": 0.3178048349028197,
                "home_win_prob": 0.3550397322849517,
                "tie_prob": 0.32715543281222853
              },
              "p2": {
                "away_win_prob": 0.33233878304386183,
                "home_win_prob": 0.35295621661678267,
                "tie_prob": 0.3147050003393554
              },
              "p3": {
                "away_win_prob": 0.32234754406426175,
                "home_win_prob": 0.36018458826211247,
                "tie_prob": 0.3174678676736258
              }
            },
            "total_line_used": 5.5,
            "under_odds": 110.0
          },
          {
            "away": "Edmonton Oilers",
            "away_ml_odds": 114.0,
            "away_pl_+1.5_odds": -225.0,
            "date": "2026-03-26",
            "home": "Vegas Golden Knights",
            "home_ml_odds": -135.0,
            "home_pl_-1.5_odds": 185.0,
            "model_total": 6.222833333333333,
            "over_odds": -110.0,
            "p_away_ml": 0.4315,
            "p_away_pl_+1.5": 0.7178333333333333,
            "p_home_ml": 0.5685,
            "p_home_pl_-1.5": 0.2821666666666667,
            "p_over": 0.4356666666666666,
            "p_under": 0.5643333333333334,
            "pl_line_used": 1.5,
            "proj_away_goals": 2.925333333333333,
            "proj_home_goals": 3.2975,
            "segments": {
              "final": {
                "away_win_prob": 0.36090234733446297,
                "home_win_prob": 0.47555385038668574,
                "tie_prob": 0.16354380227885124
              },
              "ot": {
                "no_prob": 0.8364561977211488,
                "yes_prob": 0.16354380227885124
              },
              "p1": {
                "away_win_prob": 0.31211081592142453,
                "home_win_prob": 0.376716306198235,
                "tie_prob": 0.3111728778803405
              },
              "p2": {
                "away_win_prob": 0.31753256335658525,
                "home_win_prob": 0.3827360052889966,
                "tie_prob": 0.29973143135441815
              },
              "p3": {
                "away_win_prob": 0.31893332562965293,
                "home_win_prob": 0.37866364980502965,
                "tie_prob": 0.3024030245653175
              }
            },
            "total_line_used": 6.5,
            "under_odds": -110.0
          },
          {
            "away": "Colorado Avalanche",
            "away_ml_odds": -185.0,
            "away_pl_+1.5_odds": null,
            "date": "2026-03-26",
            "home": "Winnipeg Jets",
            "home_ml_odds": 154.0,
            "home_pl_-1.5_odds": null,
            "model_total": 6.460666666666667,
            "over_odds": 105.0,
            "p_away_ml": 0.5121666666666667,
            "p_away_pl_+1.5": 0.78,
            "p_home_ml": 0.4878333333333333,
            "p_home_pl_-1.5": 0.22,
            "p_over": 0.4728333333333333,
            "p_under": 0.5271666666666667,
            "pl_line_used": 1.5,
            "proj_away_goals": 3.270166666666667,
            "proj_home_goals": 3.1905,
            "segments": {
              "final": {
                "away_win_prob": 0.4303211739591699,
                "home_win_prob": 0.4077946363728597,
                "tie_prob": 0.16188418966797044
              },
              "ot": {
                "no_prob": 0.8381158103320295,
                "yes_prob": 0.16188418966797044
              },
              "p1": {
                "away_win_prob": 0.3496136342411573,
                "home_win_prob": 0.34589330208397273,
                "tie_prob": 0.30449306367486995
              },
              "p2": {
                "away_win_prob": 0.36626224154442855,
                "home_win_prob": 0.34037289562558953,
                "tie_prob": 0.2933648628299818
              },
              "p3": {
                "away_win_prob": 0.35525660726992053,
                "home_win_prob": 0.3478597676308482,
                "tie_prob": 0.2968836250992311
              }
            },
            "total_line_used": 6.5,
            "under_odds": -125.0
          }
        ]
      },
      "recommendations": {
        "count": 7,
        "rows": [
          {
            "away": "Columbus Blue Jackets",
            "conf": 0.3106666666666666,
            "ev": 0.1248785529715762,
            "home": "Montréal Canadiens",
            "market": "PL",
            "price": -258.0,
            "prob": 0.8106666666666666,
            "side": "Columbus Blue Jackets +1.5",
            "totals_line": 6.5
          },
          {
            "away": "Pittsburgh Penguins",
            "conf": 0.2855,
            "ev": 0.168670731707317,
            "home": "Ottawa Senators",
            "market": "PL",
            "price": -205.0,
            "prob": 0.7855,
            "side": "Pittsburgh Penguins +1.5",
            "totals_line": 5.5
          },
          {
            "away": "Seattle Kraken",
            "conf": 0.285,
            "ev": 0.4676086956521739,
            "home": "Tampa Bay Lightning",
            "market": "PL",
            "price": -115.0,
            "prob": 0.785,
            "side": "Seattle Kraken +1.5",
            "totals_line": 6.5
          },
          {
            "away": "New Jersey Devils",
            "conf": 0.2845,
            "ev": 0.0805377358490564,
            "home": "Nashville Predators",
            "market": "PL",
            "price": -265.0,
            "prob": 0.7845,
            "side": "New Jersey Devils +1.5",
            "totals_line": 5.5
          },
          {
            "away": "Chicago Blackhawks",
            "conf": 0.2794999999999999,
            "ev": 0.2008513513513513,
            "home": "Philadelphia Flyers",
            "market": "PL",
            "price": -185.0,
            "prob": 0.7795,
            "side": "Chicago Blackhawks +1.5",
            "totals_line": 5.5
          },
          {
            "away": "Washington Capitals",
            "conf": 0.2746666666666666,
            "ev": 0.1659124579124579,
            "home": "Utah Mammoth",
            "market": "PL",
            "price": -198.0,
            "prob": 0.7746666666666666,
            "side": "Washington Capitals +1.5",
            "totals_line": 5.5
          },
          {
            "away": "Edmonton Oilers",
            "conf": 0.2178333333333333,
            "ev": 0.0368703703703703,
            "home": "Vegas Golden Knights",
            "market": "PL",
            "price": -225.0,
            "prob": 0.7178333333333333,
            "side": "Edmonton Oilers +1.5",
            "totals_line": 6.5
          }
        ]
      },
      "reconciliation": null
    },
    "props": {
      "recommendations": {
        "count": 61,
        "rows": [
          {
            "book": null,
            "edge_reasons": "MODEL OVR · CONF60+ · MATCHUP+",
            "edge_score": 0.6950273452565997,
            "ev": 0.0,
            "line": 1.5,
            "market": "SOG",
            "opp": "NSH",
            "player": "Timo Meier",
            "price": null,
            "prob": 0.923353672466571,
            "side": "Over",
            "team": "NJD"
          },
          {
            "book": null,
            "edge_reasons": "MODEL OVR · CONF60+ · MATCHUP+",
            "edge_score": 0.6802674082591217,
            "ev": 0.0,
            "line": 1.5,
            "market": "SOG",
            "opp": "CGY",
            "player": "Cutter Gauthier",
            "price": null,
            "prob": 0.9454633282425824,
            "side": "Over",
            "team": "ANA"
          },
          {
            "book": null,
            "edge_reasons": "MODEL OVR · CONF60+ · MATCHUP+",
            "edge_score": 0.6535781815726958,
            "ev": 0.0,
            "line": 1.5,
            "market": "SOG",
            "opp": "SEA",
            "player": "Darren Raddysh",
            "price": null,
            "prob": 0.915845526345344,
            "side": "Over",
            "team": "TBL"
          },
          {
            "book": null,
            "edge_reasons": "MODEL OVR · CONF60+ · MATCHUP+",
            "edge_score": 0.6437147216081347,
            "ev": 0.0,
            "line": 1.5,
            "market": "SOG",
            "opp": "CHI",
            "player": "Owen Tippett",
            "price": null,
            "prob": 0.856570280963235,
            "side": "Over",
            "team": "PHI"
          },
          {
            "book": null,
            "edge_reasons": "MODEL OVR · CONF60+",
            "edge_score": 0.6257737118044979,
            "ev": 0.0,
            "line": 1.5,
            "market": "SOG",
            "opp": "WSH",
            "player": "Clayton Keller",
            "price": null,
            "prob": 0.9023818138576982,
            "side": "Over",
            "team": "UTA"
          },
          {
            "book": null,
            "edge_reasons": "MODEL OVR · CONF60+",
            "edge_score": 0.606281680294186,
            "ev": 0.0,
            "line": 1.5,
            "market": "SOG",
            "opp": "STL",
            "player": "Macklin Celebrini",
            "price": null,
            "prob": 0.8643546639477538,
            "side": "Over",
            "team": "SJS"
          },
          {
            "book": null,
            "edge_reasons": "MODEL OVR · CONF60+",
            "edge_score": 0.6044921016428257,
            "ev": 0.0,
            "line": 1.5,
            "market": "SOG",
            "opp": "MTL",
            "player": "Zach Werenski",
            "price": null,
            "prob": 0.8777488207936152,
            "side": "Over",
            "team": "CBJ"
          },
          {
            "book": null,
            "edge_reasons": "MODEL OVR · CONF60+ · MATCHUP+",
            "edge_score": 0.5999670211881458,
            "ev": 0.0,
            "line": 1.5,
            "market": "SOG",
            "opp": "FLA",
            "player": "Kirill Kaprizov",
            "price": null,
            "prob": 0.8507224752563087,
            "side": "Over",
            "team": "MIN"
          },
          {
            "book": null,
            "edge_reasons": "MODEL OVR · CONF60+",
            "edge_score": 0.5974421928596116,
            "ev": 0.0,
            "line": 1.5,
            "market": "SOG",
            "opp": "DAL",
            "player": "Bo Horvat",
            "price": null,
            "prob": 0.8904753921847893,
            "side": "Over",
            "team": "NYI"
          },
          {
            "book": null,
            "edge_reasons": "MODEL OVR · CONF60+ · MATCHUP+",
            "edge_score": 0.5970319570226734,
            "ev": 0.0,
            "line": 1.5,
            "market": "SOG",
            "opp": "FLA",
            "player": "Matt Boldy",
            "price": null,
            "prob": 0.8470536450494682,
            "side": "Over",
            "team": "MIN"
          },
          {
            "book": null,
            "edge_reasons": "MODEL OVR · CONF60+ · MATCHUP+",
            "edge_score": 0.5970258581656468,
            "ev": 0.0,
            "line": 2.5,
            "market": "SOG",
            "opp": "CGY",
            "player": "Cutter Gauthier",
            "price": null,
            "prob": 0.8414113906257389,
            "side": "Over",
            "team": "ANA"
          },
          {
            "book": null,
            "edge_reasons": "MODEL OVR · CONF60+ · MATCHUP+",
            "edge_score": 0.5945333257441745,
            "ev": 0.0,
            "line": 1.5,
            "market": "SOG",
            "opp": "ANA",
            "player": "Matt Coronato",
            "price": null,
            "prob": 0.8382957250988985,
            "side": "Over",
            "team": "CGY"
          },
          {
            "book": null,
            "edge_reasons": "MODEL OVR · CONF60+ · MATCHUP+",
            "edge_score": 0.5903951998304181,
            "ev": 0.0,
            "line": 2.5,
            "market": "SOG",
            "opp": "NSH",
            "player": "Timo Meier",
            "price": null,
            "prob": 0.7925634906838439,
            "side": "Over",
            "team": "NJD"
          },
          {
            "book": null,
            "edge_reasons": "MODEL OVR · CONF60+",
            "edge_score": 0.5888880898107145,
            "ev": 0.0,
            "line": 1.5,
            "market": "SOG",
            "opp": "VAN",
            "player": "Anton Forsberg",
            "price": null,
            "prob": 0.8602142498549501,
            "side": "Over",
            "team": "LAK"
          },
          {
            "book": null,
            "edge_reasons": "MODEL OVR · CONF60+ · MATCHUP+",
            "edge_score": 0.5847814089200478,
            "ev": 0.0,
            "line": 1.5,
            "market": "SOG",
            "opp": "CGY",
            "player": "Ian Moore",
            "price": null,
            "prob": 0.8261058290687402,
            "side": "Over",
            "team": "ANA"
          },
          {
            "book": null,
            "edge_reasons": "MODEL OVR · CONF60+",
            "edge_score": 0.5811711633757217,
            "ev": 0.0,
            "line": 1.5,
            "market": "SOG",
            "opp": "DAL",
            "player": "Matthew Schaefer",
            "price": null,
            "prob": 0.870136605329927,
            "side": "Over",
            "team": "NYI"
          },
          {
            "book": null,
            "edge_reasons": "MODEL OVR · CONF60+",
            "edge_score": 0.5771821996305413,
            "ev": 0.0,
            "line": 1.5,
            "market": "SOG",
            "opp": "PIT",
            "player": "Brady Tkachuk",
            "price": null,
            "prob": 0.8377125563890057,
            "side": "Over",
            "team": "OTT"
          },
          {
            "book": null,
            "edge_reasons": "MODEL OVR · CONF60+ · MATCHUP+",
            "edge_score": 0.5763474970939801,
            "ev": 0.0,
            "line": 1.5,
            "market": "SOG",
            "opp": "CGY",
            "player": "Beckett Sennecke",
            "price": null,
            "prob": 0.8155634392861556,
            "side": "Over",
            "team": "ANA"
          },
          {
            "book": null,
            "edge_reasons": "MODEL OVR · CONF60+",
            "edge_score": 0.5713334454211686,
            "ev": 0.0,
            "line": 1.5,
            "market": "SOG",
            "opp": "SJS",
            "player": "Jimmy Snuggerud",
            "price": null,
            "prob": 0.8264890823350532,
            "side": "Over",
            "team": "STL"
          },
          {
            "book": null,
            "edge_reasons": "MODEL OVR · CONF60+ · MATCHUP+",
            "edge_score": 0.5686295537888754,
            "ev": 0.0,
            "line": 1.5,
            "market": "SOG",
            "opp": "NSH",
            "player": "Arseny Gritsyuk",
            "price": null,
            "prob": 0.7653564331319155,
            "side": "Over",
            "team": "NJD"
          },
          {
            "book": null,
            "edge_reasons": "MODEL OVR · CONF60+",
            "edge_score": 0.5676600900216795,
            "ev": 0.0,
            "line": 1.5,
            "market": "SOG",
            "opp": "LAK",
            "player": "Linus Karlsson",
            "price": null,
            "prob": 0.8356501393184974,
            "side": "Over",
            "team": "VAN"
          },
          {
            "book": null,
            "edge_reasons": "MODEL OVR · CONF60+ · MATCHUP+",
            "edge_score": 0.5660898691324424,
            "ev": 0.0,
            "line": 1.5,
            "market": "SOG",
            "opp": "SEA",
            "player": "Nikita Kucherov",
            "price": null,
            "prob": 0.8064851357950273,
            "side": "Over",
            "team": "TBL"
          },
          {
            "book": null,
            "edge_reasons": "MODEL OVR · CONF60+ · MATCHUP+",
            "edge_score": 0.5627405982383397,
            "ev": 0.0,
            "line": 1.5,
            "market": "SOG",
            "opp": "CGY",
            "player": "Leo Carlsson",
            "price": null,
            "prob": 0.7985548157166049,
            "side": "Over",
            "team": "ANA"
          },
          {
            "book": null,
            "edge_reasons": "MODEL OVR · CONF60+",
            "edge_score": 0.5616013531817466,
            "ev": 0.0,
            "line": 1.5,
            "market": "SOG",
            "opp": "VAN",
            "player": "Trevor Moore",
            "price": null,
            "prob": 0.8261058290687402,
            "side": "Over",
            "team": "LAK"
          },
          {
            "book": null,
            "edge_reasons": "MODEL OVR · CONF60+",
            "edge_score": 0.5611948965653583,
            "ev": 0.0,
            "line": 1.5,
            "market": "SOG",
            "opp": "LAK",
            "player": "Drew O'Connor",
            "price": null,
            "prob": 0.8275686474980959,
            "side": "Over",
            "team": "VAN"
          },
          {
            "book": null,
            "edge_reasons": "MODEL OVR · CONF60+",
            "edge_score": 0.560940687994068,
            "ev": 0.0,
            "line": 1.5,
            "market": "SOG",
            "opp": "PHI",
            "player": "Connor Bedard",
            "price": null,
            "prob": 0.8467707744024588,
            "side": "Over",
            "team": "CHI"
          },
          {
            "book": null,
            "edge_reasons": "MODEL OVR · CONF60+",
            "edge_score": 0.558533881407328,
            "ev": 0.0,
            "line": 1.5,
            "market": "SOG",
            "opp": "EDM",
            "player": "Jack Eichel",
            "price": null,
            "prob": 0.8418400028694347,
            "side": "Over",
            "team": "VGK"
          },
          {
            "book": null,
            "edge_reasons": "MODEL OVR · CONF60+ · MATCHUP-",
            "edge_score": 0.5579210658958769,
            "ev": 0.0,
            "line": 1.5,
            "market": "SOG",
            "opp": "WPG",
            "player": "Nathan MacKinnon",
            "price": null,
            "prob": 0.8449085493392168,
            "side": "Over",
            "team": "COL"
          },
          {
            "book": null,
            "edge_reasons": "MODEL OVR · CONF60+ · MATCHUP-",
            "edge_score": 0.5578762055187009,
            "ev": 0.0,
            "line": 1.5,
            "market": "SOG",
            "opp": "NJD",
            "player": "Reid Schaefer",
            "price": null,
            "prob": 0.870136605329927,
            "side": "Over",
            "team": "NSH"
          },
          {
            "book": null,
            "edge_reasons": "MODEL OVR · CONF60+",
            "edge_score": 0.5567769955593949,
            "ev": 0.0,
            "line": 1.5,
            "market": "SOG",
            "opp": "MIN",
            "player": "Matthew Tkachuk",
            "price": null,
            "prob": 0.8377125563890057,
            "side": "Over",
            "team": "FLA"
          },
          {
            "book": null,
            "edge_reasons": "MODEL OVR · CONF60+",
            "edge_score": 0.5559116874685404,
            "ev": 0.0,
            "line": 1.5,
            "market": "SOG",
            "opp": "SJS",
            "player": "Dylan Holloway",
            "price": null,
            "prob": 0.8072118848942679,
            "side": "Over",
            "team": "STL"
          },
          {
            "book": null,
            "edge_reasons": "MODEL OVR · CONF60+",
            "edge_score": 0.5542436859372717,
            "ev": 0.0,
            "line": 1.5,
            "market": "SOG",
            "opp": "SJS",
            "player": "Jordan Kyrou",
            "price": null,
            "prob": 0.8051268829801821,
            "side": "Over",
            "team": "STL"
          },
          {
            "book": null,
            "edge_reasons": "MODEL OVR · CONF60+",
            "edge_score": 0.5535819905665781,
            "ev": 0.0,
            "line": 1.5,
            "market": "SOG",
            "opp": "EDM",
            "player": "William Karlsson",
            "price": null,
            "prob": 0.8356501393184974,
            "side": "Over",
            "team": "VGK"
          },
          {
            "book": null,
            "edge_reasons": "MODEL OVR · CONF60+ · MATCHUP+",
            "edge_score": 0.5518921162223475,
            "ev": 0.0,
            "line": 1.5,
            "market": "SOG",
            "opp": "ANA",
            "player": "Blake Coleman",
            "price": null,
            "prob": 0.7849942131966147,
            "side": "Over",
            "team": "CGY"
          },
          {
            "book": null,
            "edge_reasons": "MODEL OVR · CONF60+ · MATCHUP-",
            "edge_score": 0.5499383211387193,
            "ev": 0.0,
            "line": 1.5,
            "market": "SOG",
            "opp": "NJD",
            "player": "Filip Forsberg",
            "price": null,
            "prob": 0.8602142498549501,
            "side": "Over",
            "team": "NSH"
          },
          {
            "book": null,
            "edge_reasons": "MODEL OVR · CONF60+",
            "edge_score": 0.5490080662726031,
            "ev": 0.0,
            "line": 1.5,
            "market": "SOG",
            "opp": "MIN",
            "player": "Evan Rodrigues",
            "price": null,
            "prob": 0.8280013947805159,
            "side": "Over",
            "team": "FLA"
          },
          {
            "book": null,
            "edge_reasons": "MODEL OVR · CONF60+",
            "edge_score": 0.5481901991052558,
            "ev": 0.0,
            "line": 1.5,
            "market": "SOG",
            "opp": "MTL",
            "player": "Adam Fantilli",
            "price": null,
            "prob": 0.8073714426216528,
            "side": "Over",
            "team": "CBJ"
          },
          {
            "book": null,
            "edge_reasons": "MODEL OVR · CONF60+",
            "edge_score": 0.5463365884270709,
            "ev": 0.0,
            "line": 1.5,
            "market": "SOG",
            "opp": "UTA",
            "player": "Alex Ovechkin",
            "price": null,
            "prob": 0.8109661171231379,
            "side": "Over",
            "team": "WSH"
          },
          {
            "book": null,
            "edge_reasons": "MODEL OVR · CONF60+",
            "edge_score": 0.5453365360328368,
            "ev": 0.0,
            "line": 1.5,
            "market": "SOG",
            "opp": "WSH",
            "player": "Nick Schmaltz",
            "price": null,
            "prob": 0.8018353441431219,
            "side": "Over",
            "team": "UTA"
          },
          {
            "book": null,
            "edge_reasons": "MODEL OVR · CONF60+",
            "edge_score": 0.544408731727093,
            "ev": 0.0,
            "line": 1.5,
            "market": "SOG",
            "opp": "PHI",
            "player": "Oliver Moore",
            "price": null,
            "prob": 0.8261058290687402,
            "side": "Over",
            "team": "CHI"
          },
          {
            "book": null,
            "edge_reasons": "MODEL OVR · CONF60+ · MATCHUP+",
            "edge_score": 0.5424514909178872,
            "ev": 0.0,
            "line": 2.5,
            "market": "SOG",
            "opp": "SEA",
            "player": "Darren Raddysh",
            "price": null,
            "prob": 0.7769371630268334,
            "side": "Over",
            "team": "TBL"
          },
          {
            "book": null,
            "edge_reasons": "MODEL OVR · CONF60+",
            "edge_score": 0.5421492724441949,
            "ev": 0.0,
            "line": 1.5,
            "market": "SOG",
            "opp": "VAN",
            "player": "Alex Laferriere",
            "price": null,
            "prob": 0.8017907281468004,
            "side": "Over",
            "team": "LAK"
          },
          {
            "book": null,
            "edge_reasons": "MODEL OVR · CONF60+",
            "edge_score": 0.5381533573922724,
            "ev": 0.0,
            "line": 1.5,
            "market": "SOG",
            "opp": "WSH",
            "player": "Mikhail Sergachev",
            "price": null,
            "prob": 0.7928563708424163,
            "side": "Over",
            "team": "UTA"
          },
          {
            "book": null,
            "edge_reasons": "MODEL OVR · CONF60+ · MATCHUP+",
            "edge_score": 0.5379715590442192,
            "ev": 0.0,
            "line": 1.5,
            "market": "SOG",
            "opp": "FLA",
            "player": "Brock Faber",
            "price": null,
            "prob": 0.7732281475764005,
            "side": "Over",
            "team": "MIN"
          },
          {
            "book": null,
            "edge_reasons": "MODEL OVR · CONF60+ · MATCHUP+",
            "edge_score": 0.5363033620312053,
            "ev": 0.0,
            "line": 1.5,
            "market": "SOG",
            "opp": "FLA",
            "player": "Joel Eriksson Ek",
            "price": null,
            "prob": 0.7711429013101331,
            "side": "Over",
            "team": "MIN"
          },
          {
            "book": null,
            "edge_reasons": "MODEL OVR · CONF60+",
            "edge_score": 0.5360205097386324,
            "ev": 0.0,
            "line": 1.5,
            "market": "SOG",
            "opp": "MTL",
            "player": "Kirill Marchenko",
            "price": null,
            "prob": 0.7921593309133735,
            "side": "Over",
            "team": "CBJ"
          },
          {
            "book": null,
            "edge_reasons": "MODEL OVR · CONF60+",
            "edge_score": 0.5358975410431055,
            "ev": 0.0,
            "line": 1.5,
            "market": "SOG",
            "opp": "NYI",
            "player": "Jason Robertson",
            "price": null,
            "prob": 0.7763744898839031,
            "side": "Over",
            "team": "DAL"
          },
          {
            "book": null,
            "edge_reasons": "MODEL OVR · CONF60+ · MATCHUP+",
            "edge_score": 0.5300786290794753,
            "ev": 0.0,
            "line": 1.5,
            "market": "SOG",
            "opp": "ANA",
            "player": "Jonathan Huberdeau",
            "price": null,
            "prob": 0.7577273542680245,
            "side": "Over",
            "team": "CGY"
          },
          {
            "book": null,
            "edge_reasons": "MODEL OVR · CONF60+ · MATCHUP-",
            "edge_score": 0.5279145787905798,
            "ev": 0.0,
            "line": 1.5,
            "market": "SOG",
            "opp": "WPG",
            "player": "Martin Necas",
            "price": null,
            "prob": 0.8074004404575954,
            "side": "Over",
            "team": "COL"
          },
          {
            "book": null,
            "edge_reasons": "MODEL OVR · CONF60+",
            "edge_score": 0.5274793297800289,
            "ev": 0.0,
            "line": 1.5,
            "market": "SOG",
            "opp": "DAL",
            "player": "Kyle Palmieri",
            "price": null,
            "prob": 0.8030218133353109,
            "side": "Over",
            "team": "NYI"
          },
          {
            "book": null,
            "edge_reasons": "MODEL OVR · CONF60+ · MATCHUP-",
            "edge_score": 0.5237359092004882,
            "ev": 0.0,
            "line": 1.5,
            "market": "SOG",
            "opp": "WPG",
            "player": "Artturi Lehkonen",
            "price": null,
            "prob": 0.802177103469981,
            "side": "Over",
            "team": "COL"
          },
          {
            "book": null,
            "edge_reasons": "MODEL OVR · CONF60+",
            "edge_score": 0.5212550588734448,
            "ev": 0.0,
            "line": 1.5,
            "market": "SOG",
            "opp": "EDM",
            "player": "Pavel Dorofeyev",
            "price": null,
            "prob": 0.7952414747020807,
            "side": "Over",
            "team": "VGK"
          },
          {
            "book": null,
            "edge_reasons": "MODEL OVR · CONF60+",
            "edge_score": 0.5199864187942724,
            "ev": 0.0,
            "line": 1.5,
            "market": "SOG",
            "opp": "PIT",
            "player": "Dylan Cozens",
            "price": null,
            "prob": 0.7662178303436695,
            "side": "Over",
            "team": "OTT"
          },
          {
            "book": null,
            "edge_reasons": "MODEL OVR · CONF60+",
            "edge_score": 0.5150215602041055,
            "ev": 0.0,
            "line": 1.5,
            "market": "SOG",
            "opp": "VAN",
            "player": "Artemi Panarin",
            "price": null,
            "prob": 0.7678810878466887,
            "side": "Over",
            "team": "LAK"
          },
          {
            "book": null,
            "edge_reasons": "MODEL OVR · CONF60+",
            "edge_score": 0.5134431260164447,
            "ev": 0.0,
            "line": 1.5,
            "market": "SOG",
            "opp": "VAN",
            "player": "Anze Kopitar",
            "price": null,
            "prob": 0.7659080451121127,
            "side": "Over",
            "team": "LAK"
          },
          {
            "book": null,
            "edge_reasons": "MODEL OVR · CONF60+",
            "edge_score": 0.5133328883898769,
            "ev": 0.0,
            "line": 1.5,
            "market": "SOG",
            "opp": "VAN",
            "player": "Adrian Kempe",
            "price": null,
            "prob": 0.7657702480789029,
            "side": "Over",
            "team": "LAK"
          },
          {
            "book": null,
            "edge_reasons": "MODEL OVR · CONF60+ · MATCHUP-",
            "edge_score": 0.5131477389287435,
            "ev": 0.0,
            "line": 1.5,
            "market": "SOG",
            "opp": "WPG",
            "player": "Nazem Kadri",
            "price": null,
            "prob": 0.7889418906303001,
            "side": "Over",
            "team": "COL"
          },
          {
            "book": null,
            "edge_reasons": "MODEL OVR · CONF60+",
            "edge_score": 0.5092681437901992,
            "ev": 0.0,
            "line": 1.5,
            "market": "SOG",
            "opp": "WSH",
            "player": "Dylan Guenther",
            "price": null,
            "prob": 0.7567498538398248,
            "side": "Over",
            "team": "UTA"
          },
          {
            "book": null,
            "edge_reasons": "MODEL OVR · CONF60+ · MATCHUP-",
            "edge_score": 0.5022183375368859,
            "ev": 0.0,
            "line": 1.5,
            "market": "SOG",
            "opp": "WPG",
            "player": "Cale Makar",
            "price": null,
            "prob": 0.7752801388904781,
            "side": "Over",
            "team": "COL"
          },
          {
            "book": null,
            "edge_reasons": "MODEL OVR · CONF60+ · MATCHUP-",
            "edge_score": 0.4905338811350127,
            "ev": 0.0,
            "line": 1.5,
            "market": "SOG",
            "opp": "WPG",
            "player": "Brock Nelson",
            "price": null,
            "prob": 0.7606745683881364,
            "side": "Over",
            "team": "COL"
          },
          {
            "book": null,
            "edge_reasons": "MODEL OVR · CONF60+ · MATCHUP-",
            "edge_score": 0.4855348798904049,
            "ev": 0.0,
            "line": 1.5,
            "market": "SOG",
            "opp": "WPG",
            "player": "Gabriel Landeskog",
            "price": null,
            "prob": 0.7544258168323767,
            "side": "Over",
            "team": "COL"
          }
        ],
        "source": "props_recommendations_2026-03-26.csv"
      },
      "reconciliation": null
    }
  },
  "date": "2026-03-26",
  "files": {
    "edges": "data/processed/edges_sim_2026-03-26.csv",
    "game_recommendations": "data/processed/recommendations_sim_2026-03-26.csv",
    "predictions": "data/processed/predictions_sim_2026-03-26.csv",
    "props_recommendations": "data/processed/props_recommendations_2026-03-26.csv",
    "reconciliation_games": null,
    "reconciliation_props": null
  },
  "generated_at_utc": "2026-03-25T16:51:50+00:00",
  "schema_version": 2
}